{"TC":[],"VALVE":[],"ACTUATOR":[],"FLOW":[{"data":{"FLO_IPA_VALUE":0,"FLO_IPA_ACCUMULATED":18.99,"FLO_N2O_VALUE":0,"FLO_N2O_ACCUMULATED":14.167},"timestamp":71},{"data":{"FLO_IPA_VALUE":0,"FLO_IPA_ACCUMULATED":18.99,"FLO_N2O_VALUE":0,"FLO_N2O_ACCUMULATED":34.469},"timestamp":128},{"data":{"FLO_IPA_VALUE":0,"FLO_IPA_ACCUMULATED":18.99,"FLO_N2O_VALUE":0,"FLO_N2O_ACCUMULATED":34.469},"timestamp":1032},{"data":{"FLO_IPA_VALUE":0,"FLO_IPA_ACCUMULATED":18.99,"FLO_N2O_VALUE":0,"FLO_N2O_ACCUMULATED":34.469},"timestamp":1128},{"data":{"FLO_IPA_VALUE":0,"FLO_IPA_ACCUMULATED":18.99,"FLO_N2O_VALUE":0,"FLO_N2O_ACCUMULATED":34.469},"timestamp":2033},{"data":{"FLO_IPA_VALUE":0,"FLO_IPA_ACCUMULATED":18.99,"FLO_N2O_VALUE":0,"FLO_N2O_ACCUMULATED":34.469},"timestamp":2130},{"data":{"FLO_IPA_VALUE":0,"FLO_IPA_ACCUMULATED":18.99,"FLO_N2O_VALUE":0,"FLO_N2O_ACCUMULATED":34.469},"timestamp":3034},{"data":{"FLO_IPA_VALUE":0,"FLO_IPA_ACCUMULATED":18.99,"FLO_N2O_VALUE":0,"FLO_N2O_ACCUMULATED":34.469},"timestamp":3133},{"data":{"FLO_IPA_VALUE":0,"FLO_IPA_ACCUMULATED":18.99,"FLO_N2O_VALUE":0,"FLO_N2O_ACCUMULATED":34.469},"timestamp":4063},{"data":{"FLO_IPA_VALUE":0,"FLO_IPA_ACCUMULATED":18.99,"FLO_N2O_VALUE":0,"FLO_N2O_ACCUMULATED":34.469},"timestamp":4136},{"data":{"FLO_IPA_VALUE":0,"FLO_IPA_ACCUMULATED":18.99,"FLO_N2O_VALUE":0,"FLO_N2O_ACCUMULATED":34.469},"timestamp":5035},{"data":{"FLO_IPA_VALUE":0,"FLO_IPA_ACCUMULATED":18.99,"FLO_N2O_VALUE":0,"FLO_N2O_ACCUMULATED":34.469},"timestamp":5138},{"data":{"FLO_IPA_VALUE":0.001,"FLO_IPA_ACCUMULATED":18.991,"FLO_N2O_VALUE":0,"FLO_N2O_ACCUMULATED":34.469},"timestamp":6036},{"data":{"FLO_IPA_VALUE":0.001,"FLO_IPA_ACCUMULATED":18.991,"FLO_N2O_VALUE":0.217,"FLO_N2O_ACCUMULATED":34.686},"timestamp":6139},{"data":{"FLO_IPA_VALUE":0,"FLO_IPA_ACCUMULATED":18.991,"FLO_N2O_VALUE":0.217,"FLO_N2O_ACCUMULATED":34.686},"timestamp":7038},{"data":{"FLO_IPA_VALUE":0,"FLO_IPA_ACCUMULATED":18.991,"FLO_N2O_VALUE":0.198,"FLO_N2O_ACCUMULATED":34.884},"timestamp":7140},{"data":{"FLO_IPA_VALUE":0,"FLO_IPA_ACCUMULATED":18.991,"FLO_N2O_VALUE":0.198,"FLO_N2O_ACCUMULATED":34.884},"timestamp":8057},{"data":{"FLO_IPA_VALUE":0,"FLO_IPA_ACCUMULATED":18.991,"FLO_N2O_VALUE":0.434,"FLO_N2O_ACCUMULATED":35.318},"timestamp":8142},{"data":{"FLO_IPA_VALUE":0,"FLO_IPA_ACCUMULATED":18.991,"FLO_N2O_VALUE":0.434,"FLO_N2O_ACCUMULATED":35.318},"timestamp":9065},{"data":{"FLO_IPA_VALUE":0,"FLO_IPA_ACCUMULATED":18.991,"FLO_N2O_VALUE":0.475,"FLO_N2O_ACCUMULATED":35.793},"timestamp":9144},{"data":{"FLO_IPA_VALUE":0.001,"FLO_IPA_ACCUMULATED":18.992,"FLO_N2O_VALUE":0.475,"FLO_N2O_ACCUMULATED":35.793},"timestamp":10042},{"data":{"FLO_IPA_VALUE":0.001,"FLO_IPA_ACCUMULATED":18.992,"FLO_N2O_VALUE":0.356,"FLO_N2O_ACCUMULATED":36.149},"timestamp":10146},{"data":{"FLO_IPA_VALUE":0.001,"FLO_IPA_ACCUMULATED":18.993,"FLO_N2O_VALUE":0.356,"FLO_N2O_ACCUMULATED":36.149},"timestamp":11044},{"data":{"FLO_IPA_VALUE":0.001,"FLO_IPA_ACCUMULATED":18.993,"FLO_N2O_VALUE":0.165,"FLO_N2O_ACCUMULATED":36.314},"timestamp":11147},{"data":{"FLO_IPA_VALUE":0,"FLO_IPA_ACCUMULATED":18.993,"FLO_N2O_VALUE":0.165,"FLO_N2O_ACCUMULATED":36.314},"timestamp":12045},{"data":{"FLO_IPA_VALUE":0,"FLO_IPA_ACCUMULATED":18.993,"FLO_N2O_VALUE":0.536,"FLO_N2O_ACCUMULATED":36.85},"timestamp":12148},{"data":{"FLO_IPA_VALUE":0,"FLO_IPA_ACCUMULATED":18.993,"FLO_N2O_VALUE":0.536,"FLO_N2O_ACCUMULATED":36.85},"timestamp":13047},{"data":{"FLO_IPA_VALUE":0,"FLO_IPA_ACCUMULATED":18.993,"FLO_N2O_VALUE":0.502,"FLO_N2O_ACCUMULATED":37.352},"timestamp":13150},{"data":{"FLO_IPA_VALUE":0,"FLO_IPA_ACCUMULATED":18.993,"FLO_N2O_VALUE":0.502,"FLO_N2O_ACCUMULATED":37.352},"timestamp":14074},{"data":{"FLO_IPA_VALUE":0,"FLO_IPA_ACCUMULATED":18.993,"FLO_N2O_VALUE":0.511,"FLO_N2O_ACCUMULATED":37.863},"timestamp":14151},{"data":{"FLO_IPA_VALUE":0,"FLO_IPA_ACCUMULATED":18.993,"FLO_N2O_VALUE":0.511,"FLO_N2O_ACCUMULATED":37.863},"timestamp":15048},{"data":{"FLO_IPA_VALUE":0,"FLO_IPA_ACCUMULATED":18.993,"FLO_N2O_VALUE":0.537,"FLO_N2O_ACCUMULATED":38.4},"timestamp":15155},{"data":{"FLO_IPA_VALUE":0,"FLO_IPA_ACCUMULATED":18.993,"FLO_N2O_VALUE":0.537,"FLO_N2O_ACCUMULATED":38.4},"timestamp":16049},{"data":{"FLO_IPA_VALUE":0,"FLO_IPA_ACCUMULATED":18.993,"FLO_N2O_VALUE":0.517,"FLO_N2O_ACCUMULATED":38.917},"timestamp":16155},{"data":{"FLO_IPA_VALUE":0,"FLO_IPA_ACCUMULATED":18.993,"FLO_N2O_VALUE":0.517,"FLO_N2O_ACCUMULATED":38.917},"timestamp":17051},{"data":{"FLO_IPA_VALUE":0,"FLO_IPA_ACCUMULATED":18.993,"FLO_N2O_VALUE":0.536,"FLO_N2O_ACCUMULATED":39.453},"timestamp":17156},{"data":{"FLO_IPA_VALUE":0,"FLO_IPA_ACCUMULATED":18.993,"FLO_N2O_VALUE":0.536,"FLO_N2O_ACCUMULATED":39.453},"timestamp":18051},{"data":{"FLO_IPA_VALUE":0,"FLO_IPA_ACCUMULATED":18.993,"FLO_N2O_VALUE":0.511,"FLO_N2O_ACCUMULATED":39.964},"timestamp":18160},{"data":{"FLO_IPA_VALUE":0,"FLO_IPA_ACCUMULATED":18.993,"FLO_N2O_VALUE":0.511,"FLO_N2O_ACCUMULATED":39.964},"timestamp":19052},{"data":{"FLO_IPA_VALUE":0,"FLO_IPA_ACCUMULATED":18.993,"FLO_N2O_VALUE":0.489,"FLO_N2O_ACCUMULATED":40.453},"timestamp":19186},{"data":{"FLO_IPA_VALUE":0,"FLO_IPA_ACCUMULATED":18.993,"FLO_N2O_VALUE":0.489,"FLO_N2O_ACCUMULATED":40.453},"timestamp":20054},{"data":{"FLO_IPA_VALUE":0,"FLO_IPA_ACCUMULATED":18.993,"FLO_N2O_VALUE":0.507,"FLO_N2O_ACCUMULATED":40.96},"timestamp":20163},{"data":{"FLO_IPA_VALUE":0,"FLO_IPA_ACCUMULATED":18.993,"FLO_N2O_VALUE":0.507,"FLO_N2O_ACCUMULATED":40.96},"timestamp":21054},{"data":{"FLO_IPA_VALUE":0,"FLO_IPA_ACCUMULATED":18.993,"FLO_N2O_VALUE":0.505,"FLO_N2O_ACCUMULATED":41.465},"timestamp":21164},{"data":{"FLO_IPA_VALUE":0,"FLO_IPA_ACCUMULATED":18.993,"FLO_N2O_VALUE":0.505,"FLO_N2O_ACCUMULATED":41.465},"timestamp":22052},{"data":{"FLO_IPA_VALUE":0,"FLO_IPA_ACCUMULATED":18.993,"FLO_N2O_VALUE":0.54,"FLO_N2O_ACCUMULATED":42.005},"timestamp":22166},{"data":{"FLO_IPA_VALUE":0,"FLO_IPA_ACCUMULATED":18.993,"FLO_N2O_VALUE":0.54,"FLO_N2O_ACCUMULATED":42.005},"timestamp":23052},{"data":{"FLO_IPA_VALUE":0,"FLO_IPA_ACCUMULATED":18.993,"FLO_N2O_VALUE":0.517,"FLO_N2O_ACCUMULATED":42.522},"timestamp":23167},{"data":{"FLO_IPA_VALUE":0,"FLO_IPA_ACCUMULATED":18.993,"FLO_N2O_VALUE":0.517,"FLO_N2O_ACCUMULATED":42.522},"timestamp":24056},{"data":{"FLO_IPA_VALUE":0,"FLO_IPA_ACCUMULATED":18.993,"FLO_N2O_VALUE":0.537,"FLO_N2O_ACCUMULATED":43.059},"timestamp":24170},{"data":{"FLO_IPA_VALUE":0,"FLO_IPA_ACCUMULATED":18.993,"FLO_N2O_VALUE":0.537,"FLO_N2O_ACCUMULATED":43.059},"timestamp":25056},{"data":{"FLO_IPA_VALUE":0,"FLO_IPA_ACCUMULATED":18.993,"FLO_N2O_VALUE":0.229,"FLO_N2O_ACCUMULATED":43.288},"timestamp":25171},{"data":{"FLO_IPA_VALUE":0,"FLO_IPA_ACCUMULATED":18.993,"FLO_N2O_VALUE":0.229,"FLO_N2O_ACCUMULATED":43.288},"timestamp":26057},{"data":{"FLO_IPA_VALUE":0,"FLO_IPA_ACCUMULATED":18.993,"FLO_N2O_VALUE":0,"FLO_N2O_ACCUMULATED":43.288},"timestamp":26172},{"data":{"FLO_IPA_VALUE":0,"FLO_IPA_ACCUMULATED":18.993,"FLO_N2O_VALUE":0,"FLO_N2O_ACCUMULATED":43.288},"timestamp":27057},{"data":{"FLO_IPA_VALUE":0,"FLO_IPA_ACCUMULATED":18.993,"FLO_N2O_VALUE":0.242,"FLO_N2O_ACCUMULATED":43.53},"timestamp":27174},{"data":{"FLO_IPA_VALUE":0.001,"FLO_IPA_ACCUMULATED":18.994,"FLO_N2O_VALUE":0.242,"FLO_N2O_ACCUMULATED":43.53},"timestamp":28057},{"data":{"FLO_IPA_VALUE":0.001,"FLO_IPA_ACCUMULATED":18.994,"FLO_N2O_VALUE":0.127,"FLO_N2O_ACCUMULATED":43.657},"timestamp":28176},{"data":{"FLO_IPA_VALUE":0,"FLO_IPA_ACCUMULATED":18.994,"FLO_N2O_VALUE":0.127,"FLO_N2O_ACCUMULATED":43.657},"timestamp":29058},{"data":{"FLO_IPA_VALUE":0,"FLO_IPA_ACCUMULATED":18.994,"FLO_N2O_VALUE":0.082,"FLO_N2O_ACCUMULATED":43.739},"timestamp":29177},{"data":{"FLO_IPA_VALUE":0,"FLO_IPA_ACCUMULATED":18.994,"FLO_N2O_VALUE":0.082,"FLO_N2O_ACCUMULATED":43.739},"timestamp":30085},{"data":{"FLO_IPA_VALUE":0,"FLO_IPA_ACCUMULATED":18.994,"FLO_N2O_VALUE":0.513,"FLO_N2O_ACCUMULATED":44.252},"timestamp":30180},{"data":{"FLO_IPA_VALUE":0,"FLO_IPA_ACCUMULATED":18.994,"FLO_N2O_VALUE":0.513,"FLO_N2O_ACCUMULATED":44.252},"timestamp":31061},{"data":{"FLO_IPA_VALUE":0,"FLO_IPA_ACCUMULATED":18.994,"FLO_N2O_VALUE":0.545,"FLO_N2O_ACCUMULATED":44.797},"timestamp":31182},{"data":{"FLO_IPA_VALUE":0,"FLO_IPA_ACCUMULATED":18.994,"FLO_N2O_VALUE":0.545,"FLO_N2O_ACCUMULATED":44.797},"timestamp":32062},{"data":{"FLO_IPA_VALUE":0,"FLO_IPA_ACCUMULATED":18.994,"FLO_N2O_VALUE":0.499,"FLO_N2O_ACCUMULATED":45.296},"timestamp":32182},{"data":{"FLO_IPA_VALUE":0,"FLO_IPA_ACCUMULATED":18.994,"FLO_N2O_VALUE":0.499,"FLO_N2O_ACCUMULATED":45.296},"timestamp":33064},{"data":{"FLO_IPA_VALUE":0,"FLO_IPA_ACCUMULATED":18.994,"FLO_N2O_VALUE":0.563,"FLO_N2O_ACCUMULATED":45.859},"timestamp":33184},{"data":{"FLO_IPA_VALUE":0,"FLO_IPA_ACCUMULATED":18.994,"FLO_N2O_VALUE":0.563,"FLO_N2O_ACCUMULATED":45.859},"timestamp":34063},{"data":{"FLO_IPA_VALUE":0,"FLO_IPA_ACCUMULATED":18.994,"FLO_N2O_VALUE":0.52,"FLO_N2O_ACCUMULATED":46.379},"timestamp":34186},{"data":{"FLO_IPA_VALUE":0,"FLO_IPA_ACCUMULATED":18.994,"FLO_N2O_VALUE":0.52,"FLO_N2O_ACCUMULATED":46.379},"timestamp":35108},{"data":{"FLO_IPA_VALUE":0,"FLO_IPA_ACCUMULATED":18.994,"FLO_N2O_VALUE":0.517,"FLO_N2O_ACCUMULATED":46.896},"timestamp":35190},{"data":{"FLO_IPA_VALUE":0,"FLO_IPA_ACCUMULATED":18.994,"FLO_N2O_VALUE":0.517,"FLO_N2O_ACCUMULATED":46.896},"timestamp":36067},{"data":{"FLO_IPA_VALUE":0,"FLO_IPA_ACCUMULATED":18.994,"FLO_N2O_VALUE":0.498,"FLO_N2O_ACCUMULATED":47.394},"timestamp":36189},{"data":{"FLO_IPA_VALUE":0,"FLO_IPA_ACCUMULATED":18.994,"FLO_N2O_VALUE":0.498,"FLO_N2O_ACCUMULATED":47.394},"timestamp":37067},{"data":{"FLO_IPA_VALUE":0,"FLO_IPA_ACCUMULATED":18.994,"FLO_N2O_VALUE":0.522,"FLO_N2O_ACCUMULATED":47.916},"timestamp":37191},{"data":{"FLO_IPA_VALUE":0,"FLO_IPA_ACCUMULATED":18.994,"FLO_N2O_VALUE":0.522,"FLO_N2O_ACCUMULATED":47.916},"timestamp":38067},{"data":{"FLO_IPA_VALUE":0,"FLO_IPA_ACCUMULATED":18.994,"FLO_N2O_VALUE":0.513,"FLO_N2O_ACCUMULATED":48.429},"timestamp":38192},{"data":{"FLO_IPA_VALUE":0,"FLO_IPA_ACCUMULATED":18.994,"FLO_N2O_VALUE":0.513,"FLO_N2O_ACCUMULATED":48.429},"timestamp":39069},{"data":{"FLO_IPA_VALUE":0,"FLO_IPA_ACCUMULATED":18.994,"FLO_N2O_VALUE":0.539,"FLO_N2O_ACCUMULATED":48.968},"timestamp":39194},{"data":{"FLO_IPA_VALUE":0,"FLO_IPA_ACCUMULATED":18.994,"FLO_N2O_VALUE":0.539,"FLO_N2O_ACCUMULATED":48.968},"timestamp":40070},{"data":{"FLO_IPA_VALUE":0,"FLO_IPA_ACCUMULATED":18.994,"FLO_N2O_VALUE":0.54,"FLO_N2O_ACCUMULATED":49.508},"timestamp":40243},{"data":{"FLO_IPA_VALUE":0,"FLO_IPA_ACCUMULATED":18.994,"FLO_N2O_VALUE":0.54,"FLO_N2O_ACCUMULATED":49.508},"timestamp":41071},{"data":{"FLO_IPA_VALUE":0,"FLO_IPA_ACCUMULATED":18.994,"FLO_N2O_VALUE":0.507,"FLO_N2O_ACCUMULATED":50.015},"timestamp":41198},{"data":{"FLO_IPA_VALUE":0,"FLO_IPA_ACCUMULATED":18.994,"FLO_N2O_VALUE":0.507,"FLO_N2O_ACCUMULATED":50.015},"timestamp":42071},{"data":{"FLO_IPA_VALUE":0,"FLO_IPA_ACCUMULATED":18.994,"FLO_N2O_VALUE":0.49,"FLO_N2O_ACCUMULATED":50.505},"timestamp":42200},{"data":{"FLO_IPA_VALUE":0,"FLO_IPA_ACCUMULATED":18.994,"FLO_N2O_VALUE":0.49,"FLO_N2O_ACCUMULATED":50.505},"timestamp":43073},{"data":{"FLO_IPA_VALUE":0,"FLO_IPA_ACCUMULATED":18.994,"FLO_N2O_VALUE":0.531,"FLO_N2O_ACCUMULATED":51.036},"timestamp":43202},{"data":{"FLO_IPA_VALUE":0,"FLO_IPA_ACCUMULATED":18.994,"FLO_N2O_VALUE":0.531,"FLO_N2O_ACCUMULATED":51.036},"timestamp":44074},{"data":{"FLO_IPA_VALUE":0,"FLO_IPA_ACCUMULATED":18.994,"FLO_N2O_VALUE":0.52,"FLO_N2O_ACCUMULATED":51.556},"timestamp":44203},{"data":{"FLO_IPA_VALUE":0,"FLO_IPA_ACCUMULATED":18.994,"FLO_N2O_VALUE":0.52,"FLO_N2O_ACCUMULATED":51.556},"timestamp":45075},{"data":{"FLO_IPA_VALUE":0,"FLO_IPA_ACCUMULATED":18.994,"FLO_N2O_VALUE":0.584,"FLO_N2O_ACCUMULATED":52.14},"timestamp":45206},{"data":{"FLO_IPA_VALUE":0,"FLO_IPA_ACCUMULATED":18.994,"FLO_N2O_VALUE":0.584,"FLO_N2O_ACCUMULATED":52.14},"timestamp":46076},{"data":{"FLO_IPA_VALUE":0,"FLO_IPA_ACCUMULATED":18.994,"FLO_N2O_VALUE":0.507,"FLO_N2O_ACCUMULATED":52.647},"timestamp":46235},{"data":{"FLO_IPA_VALUE":0,"FLO_IPA_ACCUMULATED":18.994,"FLO_N2O_VALUE":0.507,"FLO_N2O_ACCUMULATED":52.647},"timestamp":47076},{"data":{"FLO_IPA_VALUE":0,"FLO_IPA_ACCUMULATED":18.994,"FLO_N2O_VALUE":0.517,"FLO_N2O_ACCUMULATED":53.164},"timestamp":47208},{"data":{"FLO_IPA_VALUE":0,"FLO_IPA_ACCUMULATED":18.994,"FLO_N2O_VALUE":0.517,"FLO_N2O_ACCUMULATED":53.164},"timestamp":48078},{"data":{"FLO_IPA_VALUE":0,"FLO_IPA_ACCUMULATED":18.994,"FLO_N2O_VALUE":0.505,"FLO_N2O_ACCUMULATED":53.669},"timestamp":48211},{"data":{"FLO_IPA_VALUE":0,"FLO_IPA_ACCUMULATED":18.994,"FLO_N2O_VALUE":0.505,"FLO_N2O_ACCUMULATED":53.669},"timestamp":49078},{"data":{"FLO_IPA_VALUE":0,"FLO_IPA_ACCUMULATED":18.994,"FLO_N2O_VALUE":0.513,"FLO_N2O_ACCUMULATED":54.182},"timestamp":49212},{"data":{"FLO_IPA_VALUE":0,"FLO_IPA_ACCUMULATED":18.994,"FLO_N2O_VALUE":0.513,"FLO_N2O_ACCUMULATED":54.182},"timestamp":50080},{"data":{"FLO_IPA_VALUE":0,"FLO_IPA_ACCUMULATED":18.994,"FLO_N2O_VALUE":0.495,"FLO_N2O_ACCUMULATED":54.677},"timestamp":50214},{"data":{"FLO_IPA_VALUE":0,"FLO_IPA_ACCUMULATED":18.994,"FLO_N2O_VALUE":0.495,"FLO_N2O_ACCUMULATED":54.677},"timestamp":51080},{"data":{"FLO_IPA_VALUE":0,"FLO_IPA_ACCUMULATED":18.994,"FLO_N2O_VALUE":0.402,"FLO_N2O_ACCUMULATED":55.079},"timestamp":51215},{"data":{"FLO_IPA_VALUE":0,"FLO_IPA_ACCUMULATED":18.994,"FLO_N2O_VALUE":0.402,"FLO_N2O_ACCUMULATED":55.079},"timestamp":52087},{"data":{"FLO_IPA_VALUE":0,"FLO_IPA_ACCUMULATED":18.994,"FLO_N2O_VALUE":0,"FLO_N2O_ACCUMULATED":55.079},"timestamp":52218},{"data":{"FLO_IPA_VALUE":0,"FLO_IPA_ACCUMULATED":18.994,"FLO_N2O_VALUE":0,"FLO_N2O_ACCUMULATED":55.079},"timestamp":53082},{"data":{"FLO_IPA_VALUE":0,"FLO_IPA_ACCUMULATED":18.994,"FLO_N2O_VALUE":0,"FLO_N2O_ACCUMULATED":55.079},"timestamp":53218},{"data":{"FLO_IPA_VALUE":0,"FLO_IPA_ACCUMULATED":18.994,"FLO_N2O_VALUE":0,"FLO_N2O_ACCUMULATED":55.079},"timestamp":54088},{"data":{"FLO_IPA_VALUE":0,"FLO_IPA_ACCUMULATED":18.994,"FLO_N2O_VALUE":0,"FLO_N2O_ACCUMULATED":55.079},"timestamp":54220},{"data":{"FLO_IPA_VALUE":0,"FLO_IPA_ACCUMULATED":18.994,"FLO_N2O_VALUE":0,"FLO_N2O_ACCUMULATED":55.079},"timestamp":55083},{"data":{"FLO_IPA_VALUE":0,"FLO_IPA_ACCUMULATED":18.994,"FLO_N2O_VALUE":0,"FLO_N2O_ACCUMULATED":55.079},"timestamp":55222},{"data":{"FLO_IPA_VALUE":0,"FLO_IPA_ACCUMULATED":18.994,"FLO_N2O_VALUE":0,"FLO_N2O_ACCUMULATED":55.079},"timestamp":56085},{"data":{"FLO_IPA_VALUE":0,"FLO_IPA_ACCUMULATED":18.994,"FLO_N2O_VALUE":0,"FLO_N2O_ACCUMULATED":55.079},"timestamp":56223},{"data":{"FLO_IPA_VALUE":0,"FLO_IPA_ACCUMULATED":18.994,"FLO_N2O_VALUE":0,"FLO_N2O_ACCUMULATED":55.079},"timestamp":57085},{"data":{"FLO_IPA_VALUE":0,"FLO_IPA_ACCUMULATED":18.994,"FLO_N2O_VALUE":0,"FLO_N2O_ACCUMULATED":55.079},"timestamp":57225},{"data":{"FLO_IPA_VALUE":0,"FLO_IPA_ACCUMULATED":18.994,"FLO_N2O_VALUE":0,"FLO_N2O_ACCUMULATED":55.079},"timestamp":58087},{"data":{"FLO_IPA_VALUE":0,"FLO_IPA_ACCUMULATED":18.994,"FLO_N2O_VALUE":0.154,"FLO_N2O_ACCUMULATED":55.233},"timestamp":58227},{"data":{"FLO_IPA_VALUE":0,"FLO_IPA_ACCUMULATED":18.994,"FLO_N2O_VALUE":0.154,"FLO_N2O_ACCUMULATED":55.233},"timestamp":59090},{"data":{"FLO_IPA_VALUE":0,"FLO_IPA_ACCUMULATED":18.994,"FLO_N2O_VALUE":0.517,"FLO_N2O_ACCUMULATED":55.75},"timestamp":59229},{"data":{"FLO_IPA_VALUE":0,"FLO_IPA_ACCUMULATED":18.994,"FLO_N2O_VALUE":0.517,"FLO_N2O_ACCUMULATED":55.75},"timestamp":60089},{"data":{"FLO_IPA_VALUE":0,"FLO_IPA_ACCUMULATED":18.994,"FLO_N2O_VALUE":0.548,"FLO_N2O_ACCUMULATED":56.298},"timestamp":60231},{"data":{"FLO_IPA_VALUE":0,"FLO_IPA_ACCUMULATED":18.994,"FLO_N2O_VALUE":0.548,"FLO_N2O_ACCUMULATED":56.298},"timestamp":61090},{"data":{"FLO_IPA_VALUE":0,"FLO_IPA_ACCUMULATED":18.994,"FLO_N2O_VALUE":0.549,"FLO_N2O_ACCUMULATED":56.847},"timestamp":61232},{"data":{"FLO_IPA_VALUE":0,"FLO_IPA_ACCUMULATED":18.994,"FLO_N2O_VALUE":0.549,"FLO_N2O_ACCUMULATED":56.847},"timestamp":62090},{"data":{"FLO_IPA_VALUE":0,"FLO_IPA_ACCUMULATED":18.994,"FLO_N2O_VALUE":0.514,"FLO_N2O_ACCUMULATED":57.361},"timestamp":62233},{"data":{"FLO_IPA_VALUE":0,"FLO_IPA_ACCUMULATED":18.994,"FLO_N2O_VALUE":0.514,"FLO_N2O_ACCUMULATED":57.361},"timestamp":63092},{"data":{"FLO_IPA_VALUE":0,"FLO_IPA_ACCUMULATED":18.994,"FLO_N2O_VALUE":0.502,"FLO_N2O_ACCUMULATED":57.863},"timestamp":63236},{"data":{"FLO_IPA_VALUE":0,"FLO_IPA_ACCUMULATED":18.994,"FLO_N2O_VALUE":0.502,"FLO_N2O_ACCUMULATED":57.863},"timestamp":64092},{"data":{"FLO_IPA_VALUE":0,"FLO_IPA_ACCUMULATED":18.994,"FLO_N2O_VALUE":0,"FLO_N2O_ACCUMULATED":57.863},"timestamp":64237},{"data":{"FLO_IPA_VALUE":0,"FLO_IPA_ACCUMULATED":18.994,"FLO_N2O_VALUE":0,"FLO_N2O_ACCUMULATED":57.863},"timestamp":65094},{"data":{"FLO_IPA_VALUE":0,"FLO_IPA_ACCUMULATED":18.994,"FLO_N2O_VALUE":0,"FLO_N2O_ACCUMULATED":57.863},"timestamp":65240},{"data":{"FLO_IPA_VALUE":0,"FLO_IPA_ACCUMULATED":18.994,"FLO_N2O_VALUE":0,"FLO_N2O_ACCUMULATED":57.863},"timestamp":66094},{"data":{"FLO_IPA_VALUE":0,"FLO_IPA_ACCUMULATED":18.994,"FLO_N2O_VALUE":0,"FLO_N2O_ACCUMULATED":57.863},"timestamp":66240},{"data":{"FLO_IPA_VALUE":0,"FLO_IPA_ACCUMULATED":18.994,"FLO_N2O_VALUE":0,"FLO_N2O_ACCUMULATED":57.863},"timestamp":67096},{"data":{"FLO_IPA_VALUE":0,"FLO_IPA_ACCUMULATED":18.994,"FLO_N2O_VALUE":0,"FLO_N2O_ACCUMULATED":57.863},"timestamp":67242},{"data":{"FLO_IPA_VALUE":0,"FLO_IPA_ACCUMULATED":18.994,"FLO_N2O_VALUE":0,"FLO_N2O_ACCUMULATED":57.863},"timestamp":68096},{"data":{"FLO_IPA_VALUE":0,"FLO_IPA_ACCUMULATED":18.994,"FLO_N2O_VALUE":0.148,"FLO_N2O_ACCUMULATED":58.011},"timestamp":68243},{"data":{"FLO_IPA_VALUE":0,"FLO_IPA_ACCUMULATED":18.994,"FLO_N2O_VALUE":0.148,"FLO_N2O_ACCUMULATED":58.011},"timestamp":69097},{"data":{"FLO_IPA_VALUE":0,"FLO_IPA_ACCUMULATED":18.994,"FLO_N2O_VALUE":0.496,"FLO_N2O_ACCUMULATED":58.507},"timestamp":69245},{"data":{"FLO_IPA_VALUE":0,"FLO_IPA_ACCUMULATED":18.994,"FLO_N2O_VALUE":0.496,"FLO_N2O_ACCUMULATED":58.507},"timestamp":70099},{"data":{"FLO_IPA_VALUE":0,"FLO_IPA_ACCUMULATED":18.994,"FLO_N2O_VALUE":0.52,"FLO_N2O_ACCUMULATED":59.027},"timestamp":70249},{"data":{"FLO_IPA_VALUE":0,"FLO_IPA_ACCUMULATED":18.994,"FLO_N2O_VALUE":0.52,"FLO_N2O_ACCUMULATED":59.027},"timestamp":71100},{"data":{"FLO_IPA_VALUE":0,"FLO_IPA_ACCUMULATED":18.994,"FLO_N2O_VALUE":0.493,"FLO_N2O_ACCUMULATED":59.52},"timestamp":71249},{"data":{"FLO_IPA_VALUE":0,"FLO_IPA_ACCUMULATED":18.994,"FLO_N2O_VALUE":0.493,"FLO_N2O_ACCUMULATED":59.52},"timestamp":72101},{"data":{"FLO_IPA_VALUE":0,"FLO_IPA_ACCUMULATED":18.994,"FLO_N2O_VALUE":0.557,"FLO_N2O_ACCUMULATED":60.077},"timestamp":72251},{"data":{"FLO_IPA_VALUE":0,"FLO_IPA_ACCUMULATED":18.994,"FLO_N2O_VALUE":0.557,"FLO_N2O_ACCUMULATED":60.077},"timestamp":73102},{"data":{"FLO_IPA_VALUE":0,"FLO_IPA_ACCUMULATED":18.994,"FLO_N2O_VALUE":0.501,"FLO_N2O_ACCUMULATED":60.578},"timestamp":73252},{"data":{"FLO_IPA_VALUE":0,"FLO_IPA_ACCUMULATED":18.994,"FLO_N2O_VALUE":0.501,"FLO_N2O_ACCUMULATED":60.578},"timestamp":74103},{"data":{"FLO_IPA_VALUE":0,"FLO_IPA_ACCUMULATED":18.994,"FLO_N2O_VALUE":0.519,"FLO_N2O_ACCUMULATED":61.097},"timestamp":74254},{"data":{"FLO_IPA_VALUE":0,"FLO_IPA_ACCUMULATED":18.994,"FLO_N2O_VALUE":0.519,"FLO_N2O_ACCUMULATED":61.097},"timestamp":75104},{"data":{"FLO_IPA_VALUE":0,"FLO_IPA_ACCUMULATED":18.994,"FLO_N2O_VALUE":0.513,"FLO_N2O_ACCUMULATED":61.61},"timestamp":75256},{"data":{"FLO_IPA_VALUE":0,"FLO_IPA_ACCUMULATED":18.994,"FLO_N2O_VALUE":0.513,"FLO_N2O_ACCUMULATED":61.61},"timestamp":76106},{"data":{"FLO_IPA_VALUE":0,"FLO_IPA_ACCUMULATED":18.994,"FLO_N2O_VALUE":0.517,"FLO_N2O_ACCUMULATED":62.127},"timestamp":76257},{"data":{"FLO_IPA_VALUE":0,"FLO_IPA_ACCUMULATED":18.994,"FLO_N2O_VALUE":0.517,"FLO_N2O_ACCUMULATED":62.127},"timestamp":77105},{"data":{"FLO_IPA_VALUE":0,"FLO_IPA_ACCUMULATED":18.994,"FLO_N2O_VALUE":0.514,"FLO_N2O_ACCUMULATED":62.641},"timestamp":77259},{"data":{"FLO_IPA_VALUE":0,"FLO_IPA_ACCUMULATED":18.994,"FLO_N2O_VALUE":0.514,"FLO_N2O_ACCUMULATED":62.641},"timestamp":78107},{"data":{"FLO_IPA_VALUE":0,"FLO_IPA_ACCUMULATED":18.994,"FLO_N2O_VALUE":0.537,"FLO_N2O_ACCUMULATED":63.178},"timestamp":78261},{"data":{"FLO_IPA_VALUE":0,"FLO_IPA_ACCUMULATED":18.994,"FLO_N2O_VALUE":0.537,"FLO_N2O_ACCUMULATED":63.178},"timestamp":79116},{"data":{"FLO_IPA_VALUE":0,"FLO_IPA_ACCUMULATED":18.994,"FLO_N2O_VALUE":0.504,"FLO_N2O_ACCUMULATED":63.682},"timestamp":79261},{"data":{"FLO_IPA_VALUE":0,"FLO_IPA_ACCUMULATED":18.994,"FLO_N2O_VALUE":0.504,"FLO_N2O_ACCUMULATED":63.682},"timestamp":80109},{"data":{"FLO_IPA_VALUE":0,"FLO_IPA_ACCUMULATED":18.994,"FLO_N2O_VALUE":0.496,"FLO_N2O_ACCUMULATED":64.178},"timestamp":80265},{"data":{"FLO_IPA_VALUE":0,"FLO_IPA_ACCUMULATED":18.994,"FLO_N2O_VALUE":0.496,"FLO_N2O_ACCUMULATED":64.178},"timestamp":81110},{"data":{"FLO_IPA_VALUE":0,"FLO_IPA_ACCUMULATED":18.994,"FLO_N2O_VALUE":0.531,"FLO_N2O_ACCUMULATED":64.709},"timestamp":81270},{"data":{"FLO_IPA_VALUE":0,"FLO_IPA_ACCUMULATED":18.994,"FLO_N2O_VALUE":0.531,"FLO_N2O_ACCUMULATED":64.709},"timestamp":82111},{"data":{"FLO_IPA_VALUE":0,"FLO_IPA_ACCUMULATED":18.994,"FLO_N2O_VALUE":0.557,"FLO_N2O_ACCUMULATED":65.266},"timestamp":82268},{"data":{"FLO_IPA_VALUE":0,"FLO_IPA_ACCUMULATED":18.994,"FLO_N2O_VALUE":0.557,"FLO_N2O_ACCUMULATED":65.266},"timestamp":83112},{"data":{"FLO_IPA_VALUE":0,"FLO_IPA_ACCUMULATED":18.994,"FLO_N2O_VALUE":0.52,"FLO_N2O_ACCUMULATED":65.786},"timestamp":83271},{"data":{"FLO_IPA_VALUE":0,"FLO_IPA_ACCUMULATED":18.994,"FLO_N2O_VALUE":0.52,"FLO_N2O_ACCUMULATED":65.786},"timestamp":84113},{"data":{"FLO_IPA_VALUE":0,"FLO_IPA_ACCUMULATED":18.994,"FLO_N2O_VALUE":0.56,"FLO_N2O_ACCUMULATED":66.346},"timestamp":84272},{"data":{"FLO_IPA_VALUE":0,"FLO_IPA_ACCUMULATED":18.994,"FLO_N2O_VALUE":0.56,"FLO_N2O_ACCUMULATED":66.346},"timestamp":85115},{"data":{"FLO_IPA_VALUE":0,"FLO_IPA_ACCUMULATED":18.994,"FLO_N2O_VALUE":0.572,"FLO_N2O_ACCUMULATED":66.918},"timestamp":85292},{"data":{"FLO_IPA_VALUE":0,"FLO_IPA_ACCUMULATED":18.994,"FLO_N2O_VALUE":0.572,"FLO_N2O_ACCUMULATED":66.918},"timestamp":86115},{"data":{"FLO_IPA_VALUE":0,"FLO_IPA_ACCUMULATED":18.994,"FLO_N2O_VALUE":0.517,"FLO_N2O_ACCUMULATED":67.435},"timestamp":86283},{"data":{"FLO_IPA_VALUE":0,"FLO_IPA_ACCUMULATED":18.994,"FLO_N2O_VALUE":0.517,"FLO_N2O_ACCUMULATED":67.435},"timestamp":87116},{"data":{"FLO_IPA_VALUE":0,"FLO_IPA_ACCUMULATED":18.994,"FLO_N2O_VALUE":0.549,"FLO_N2O_ACCUMULATED":67.984},"timestamp":87277},{"data":{"FLO_IPA_VALUE":0,"FLO_IPA_ACCUMULATED":18.994,"FLO_N2O_VALUE":0.549,"FLO_N2O_ACCUMULATED":67.984},"timestamp":88116},{"data":{"FLO_IPA_VALUE":0,"FLO_IPA_ACCUMULATED":18.994,"FLO_N2O_VALUE":0.533,"FLO_N2O_ACCUMULATED":68.517},"timestamp":88279},{"data":{"FLO_IPA_VALUE":0,"FLO_IPA_ACCUMULATED":18.994,"FLO_N2O_VALUE":0.533,"FLO_N2O_ACCUMULATED":68.517},"timestamp":89118},{"data":{"FLO_IPA_VALUE":0,"FLO_IPA_ACCUMULATED":18.994,"FLO_N2O_VALUE":0.548,"FLO_N2O_ACCUMULATED":69.065},"timestamp":89281},{"data":{"FLO_IPA_VALUE":0,"FLO_IPA_ACCUMULATED":18.994,"FLO_N2O_VALUE":0.548,"FLO_N2O_ACCUMULATED":69.065},"timestamp":90118},{"data":{"FLO_IPA_VALUE":0,"FLO_IPA_ACCUMULATED":18.994,"FLO_N2O_VALUE":0.51,"FLO_N2O_ACCUMULATED":69.575},"timestamp":90282},{"data":{"FLO_IPA_VALUE":0,"FLO_IPA_ACCUMULATED":18.994,"FLO_N2O_VALUE":0.51,"FLO_N2O_ACCUMULATED":69.575},"timestamp":91123},{"data":{"FLO_IPA_VALUE":0,"FLO_IPA_ACCUMULATED":18.994,"FLO_N2O_VALUE":0.54,"FLO_N2O_ACCUMULATED":70.115},"timestamp":91284},{"data":{"FLO_IPA_VALUE":0,"FLO_IPA_ACCUMULATED":18.994,"FLO_N2O_VALUE":0.54,"FLO_N2O_ACCUMULATED":70.115},"timestamp":92122},{"data":{"FLO_IPA_VALUE":0,"FLO_IPA_ACCUMULATED":18.994,"FLO_N2O_VALUE":0.467,"FLO_N2O_ACCUMULATED":70.582},"timestamp":92287},{"data":{"FLO_IPA_VALUE":0,"FLO_IPA_ACCUMULATED":18.994,"FLO_N2O_VALUE":0.467,"FLO_N2O_ACCUMULATED":70.582},"timestamp":93123},{"data":{"FLO_IPA_VALUE":0,"FLO_IPA_ACCUMULATED":18.994,"FLO_N2O_VALUE":0.542,"FLO_N2O_ACCUMULATED":71.124},"timestamp":93288},{"data":{"FLO_IPA_VALUE":0,"FLO_IPA_ACCUMULATED":18.994,"FLO_N2O_VALUE":0.542,"FLO_N2O_ACCUMULATED":71.124},"timestamp":94123},{"data":{"FLO_IPA_VALUE":0,"FLO_IPA_ACCUMULATED":18.994,"FLO_N2O_VALUE":0.502,"FLO_N2O_ACCUMULATED":71.626},"timestamp":94290},{"data":{"FLO_IPA_VALUE":0,"FLO_IPA_ACCUMULATED":18.994,"FLO_N2O_VALUE":0.502,"FLO_N2O_ACCUMULATED":71.626},"timestamp":95126},{"data":{"FLO_IPA_VALUE":0,"FLO_IPA_ACCUMULATED":18.994,"FLO_N2O_VALUE":0.523,"FLO_N2O_ACCUMULATED":72.149},"timestamp":95291},{"data":{"FLO_IPA_VALUE":0,"FLO_IPA_ACCUMULATED":18.994,"FLO_N2O_VALUE":0.523,"FLO_N2O_ACCUMULATED":72.149},"timestamp":96160},{"data":{"FLO_IPA_VALUE":0,"FLO_IPA_ACCUMULATED":18.994,"FLO_N2O_VALUE":0.505,"FLO_N2O_ACCUMULATED":72.654},"timestamp":96293},{"data":{"FLO_IPA_VALUE":0,"FLO_IPA_ACCUMULATED":18.994,"FLO_N2O_VALUE":0.505,"FLO_N2O_ACCUMULATED":72.654},"timestamp":97128},{"data":{"FLO_IPA_VALUE":0,"FLO_IPA_ACCUMULATED":18.994,"FLO_N2O_VALUE":0.546,"FLO_N2O_ACCUMULATED":73.2},"timestamp":97295},{"data":{"FLO_IPA_VALUE":0,"FLO_IPA_ACCUMULATED":18.994,"FLO_N2O_VALUE":0.546,"FLO_N2O_ACCUMULATED":73.2},"timestamp":98128},{"data":{"FLO_IPA_VALUE":0,"FLO_IPA_ACCUMULATED":18.994,"FLO_N2O_VALUE":0.519,"FLO_N2O_ACCUMULATED":73.719},"timestamp":98297},{"data":{"FLO_IPA_VALUE":0,"FLO_IPA_ACCUMULATED":18.994,"FLO_N2O_VALUE":0.519,"FLO_N2O_ACCUMULATED":73.719},"timestamp":99127},{"data":{"FLO_IPA_VALUE":0,"FLO_IPA_ACCUMULATED":18.994,"FLO_N2O_VALUE":0.522,"FLO_N2O_ACCUMULATED":74.241},"timestamp":99298},{"data":{"FLO_IPA_VALUE":0,"FLO_IPA_ACCUMULATED":18.994,"FLO_N2O_VALUE":0.522,"FLO_N2O_ACCUMULATED":74.241},"timestamp":100130},{"data":{"FLO_IPA_VALUE":0,"FLO_IPA_ACCUMULATED":18.994,"FLO_N2O_VALUE":0.537,"FLO_N2O_ACCUMULATED":74.778},"timestamp":100300},{"data":{"FLO_IPA_VALUE":0,"FLO_IPA_ACCUMULATED":18.994,"FLO_N2O_VALUE":0.537,"FLO_N2O_ACCUMULATED":74.778},"timestamp":101135},{"data":{"FLO_IPA_VALUE":0,"FLO_IPA_ACCUMULATED":18.994,"FLO_N2O_VALUE":0.528,"FLO_N2O_ACCUMULATED":75.306},"timestamp":101300},{"data":{"FLO_IPA_VALUE":0,"FLO_IPA_ACCUMULATED":18.994,"FLO_N2O_VALUE":0.528,"FLO_N2O_ACCUMULATED":75.306},"timestamp":102131},{"data":{"FLO_IPA_VALUE":0,"FLO_IPA_ACCUMULATED":18.994,"FLO_N2O_VALUE":0.478,"FLO_N2O_ACCUMULATED":75.784},"timestamp":102302},{"data":{"FLO_IPA_VALUE":0,"FLO_IPA_ACCUMULATED":18.994,"FLO_N2O_VALUE":0.478,"FLO_N2O_ACCUMULATED":75.784},"timestamp":103131},{"data":{"FLO_IPA_VALUE":0,"FLO_IPA_ACCUMULATED":18.994,"FLO_N2O_VALUE":0.461,"FLO_N2O_ACCUMULATED":76.245},"timestamp":103303},{"data":{"FLO_IPA_VALUE":0,"FLO_IPA_ACCUMULATED":18.994,"FLO_N2O_VALUE":0.461,"FLO_N2O_ACCUMULATED":76.245},"timestamp":104132},{"data":{"FLO_IPA_VALUE":0,"FLO_IPA_ACCUMULATED":18.994,"FLO_N2O_VALUE":0.495,"FLO_N2O_ACCUMULATED":76.74},"timestamp":104306},{"data":{"FLO_IPA_VALUE":0,"FLO_IPA_ACCUMULATED":18.994,"FLO_N2O_VALUE":0.495,"FLO_N2O_ACCUMULATED":76.74},"timestamp":105132},{"data":{"FLO_IPA_VALUE":0,"FLO_IPA_ACCUMULATED":18.994,"FLO_N2O_VALUE":0.485,"FLO_N2O_ACCUMULATED":77.225},"timestamp":105307},{"data":{"FLO_IPA_VALUE":0,"FLO_IPA_ACCUMULATED":18.994,"FLO_N2O_VALUE":0.485,"FLO_N2O_ACCUMULATED":77.225},"timestamp":106136},{"data":{"FLO_IPA_VALUE":0,"FLO_IPA_ACCUMULATED":18.994,"FLO_N2O_VALUE":0.507,"FLO_N2O_ACCUMULATED":77.732},"timestamp":106308},{"data":{"FLO_IPA_VALUE":0,"FLO_IPA_ACCUMULATED":18.994,"FLO_N2O_VALUE":0.507,"FLO_N2O_ACCUMULATED":77.732},"timestamp":107134},{"data":{"FLO_IPA_VALUE":0,"FLO_IPA_ACCUMULATED":18.994,"FLO_N2O_VALUE":0.528,"FLO_N2O_ACCUMULATED":78.26},"timestamp":107324},{"data":{"FLO_IPA_VALUE":0,"FLO_IPA_ACCUMULATED":18.994,"FLO_N2O_VALUE":0.528,"FLO_N2O_ACCUMULATED":78.26},"timestamp":108135},{"data":{"FLO_IPA_VALUE":0,"FLO_IPA_ACCUMULATED":18.994,"FLO_N2O_VALUE":0.501,"FLO_N2O_ACCUMULATED":78.761},"timestamp":108312},{"data":{"FLO_IPA_VALUE":0,"FLO_IPA_ACCUMULATED":18.994,"FLO_N2O_VALUE":0.501,"FLO_N2O_ACCUMULATED":78.761},"timestamp":109136},{"data":{"FLO_IPA_VALUE":0,"FLO_IPA_ACCUMULATED":18.994,"FLO_N2O_VALUE":0.495,"FLO_N2O_ACCUMULATED":79.256},"timestamp":109315},{"data":{"FLO_IPA_VALUE":0,"FLO_IPA_ACCUMULATED":18.994,"FLO_N2O_VALUE":0.495,"FLO_N2O_ACCUMULATED":79.256},"timestamp":110138},{"data":{"FLO_IPA_VALUE":0,"FLO_IPA_ACCUMULATED":18.994,"FLO_N2O_VALUE":0.514,"FLO_N2O_ACCUMULATED":79.77},"timestamp":110317},{"data":{"FLO_IPA_VALUE":0,"FLO_IPA_ACCUMULATED":18.994,"FLO_N2O_VALUE":0.514,"FLO_N2O_ACCUMULATED":79.77},"timestamp":111139},{"data":{"FLO_IPA_VALUE":0,"FLO_IPA_ACCUMULATED":18.994,"FLO_N2O_VALUE":0.481,"FLO_N2O_ACCUMULATED":80.251},"timestamp":111318},{"data":{"FLO_IPA_VALUE":0,"FLO_IPA_ACCUMULATED":18.994,"FLO_N2O_VALUE":0.481,"FLO_N2O_ACCUMULATED":80.251},"timestamp":112162},{"data":{"FLO_IPA_VALUE":0,"FLO_IPA_ACCUMULATED":18.994,"FLO_N2O_VALUE":0.51,"FLO_N2O_ACCUMULATED":80.761},"timestamp":112318},{"data":{"FLO_IPA_VALUE":0,"FLO_IPA_ACCUMULATED":18.994,"FLO_N2O_VALUE":0.51,"FLO_N2O_ACCUMULATED":80.761},"timestamp":113141},{"data":{"FLO_IPA_VALUE":0,"FLO_IPA_ACCUMULATED":18.994,"FLO_N2O_VALUE":0.525,"FLO_N2O_ACCUMULATED":81.286},"timestamp":113320},{"data":{"FLO_IPA_VALUE":0,"FLO_IPA_ACCUMULATED":18.994,"FLO_N2O_VALUE":0.525,"FLO_N2O_ACCUMULATED":81.286},"timestamp":114142},{"data":{"FLO_IPA_VALUE":0,"FLO_IPA_ACCUMULATED":18.994,"FLO_N2O_VALUE":0.511,"FLO_N2O_ACCUMULATED":81.797},"timestamp":114322},{"data":{"FLO_IPA_VALUE":0,"FLO_IPA_ACCUMULATED":18.994,"FLO_N2O_VALUE":0.511,"FLO_N2O_ACCUMULATED":81.797},"timestamp":115143},{"data":{"FLO_IPA_VALUE":0,"FLO_IPA_ACCUMULATED":18.994,"FLO_N2O_VALUE":0.507,"FLO_N2O_ACCUMULATED":82.304},"timestamp":115324},{"data":{"FLO_IPA_VALUE":0,"FLO_IPA_ACCUMULATED":18.994,"FLO_N2O_VALUE":0.507,"FLO_N2O_ACCUMULATED":82.304},"timestamp":116143},{"data":{"FLO_IPA_VALUE":0,"FLO_IPA_ACCUMULATED":18.994,"FLO_N2O_VALUE":0.526,"FLO_N2O_ACCUMULATED":82.83},"timestamp":116325},{"data":{"FLO_IPA_VALUE":0,"FLO_IPA_ACCUMULATED":18.994,"FLO_N2O_VALUE":0.526,"FLO_N2O_ACCUMULATED":82.83},"timestamp":117147},{"data":{"FLO_IPA_VALUE":0,"FLO_IPA_ACCUMULATED":18.994,"FLO_N2O_VALUE":0.507,"FLO_N2O_ACCUMULATED":83.337},"timestamp":117347},{"data":{"FLO_IPA_VALUE":0,"FLO_IPA_ACCUMULATED":18.994,"FLO_N2O_VALUE":0.507,"FLO_N2O_ACCUMULATED":83.337},"timestamp":118145},{"data":{"FLO_IPA_VALUE":0,"FLO_IPA_ACCUMULATED":18.994,"FLO_N2O_VALUE":0.525,"FLO_N2O_ACCUMULATED":83.862},"timestamp":118328},{"data":{"FLO_IPA_VALUE":0,"FLO_IPA_ACCUMULATED":18.994,"FLO_N2O_VALUE":0.525,"FLO_N2O_ACCUMULATED":83.862},"timestamp":119147},{"data":{"FLO_IPA_VALUE":0,"FLO_IPA_ACCUMULATED":18.994,"FLO_N2O_VALUE":0.577,"FLO_N2O_ACCUMULATED":84.439},"timestamp":119330},{"data":{"FLO_IPA_VALUE":0,"FLO_IPA_ACCUMULATED":18.994,"FLO_N2O_VALUE":0.577,"FLO_N2O_ACCUMULATED":84.439},"timestamp":120147},{"data":{"FLO_IPA_VALUE":0,"FLO_IPA_ACCUMULATED":18.994,"FLO_N2O_VALUE":0.492,"FLO_N2O_ACCUMULATED":84.931},"timestamp":120334},{"data":{"FLO_IPA_VALUE":0,"FLO_IPA_ACCUMULATED":18.994,"FLO_N2O_VALUE":0.492,"FLO_N2O_ACCUMULATED":84.931},"timestamp":121149},{"data":{"FLO_IPA_VALUE":0,"FLO_IPA_ACCUMULATED":18.994,"FLO_N2O_VALUE":0.557,"FLO_N2O_ACCUMULATED":85.488},"timestamp":121335},{"data":{"FLO_IPA_VALUE":0,"FLO_IPA_ACCUMULATED":18.994,"FLO_N2O_VALUE":0.557,"FLO_N2O_ACCUMULATED":85.488},"timestamp":122149},{"data":{"FLO_IPA_VALUE":0,"FLO_IPA_ACCUMULATED":18.994,"FLO_N2O_VALUE":0.546,"FLO_N2O_ACCUMULATED":86.034},"timestamp":122337},{"data":{"FLO_IPA_VALUE":0,"FLO_IPA_ACCUMULATED":18.994,"FLO_N2O_VALUE":0.546,"FLO_N2O_ACCUMULATED":86.034},"timestamp":123170},{"data":{"FLO_IPA_VALUE":0,"FLO_IPA_ACCUMULATED":18.994,"FLO_N2O_VALUE":0.52,"FLO_N2O_ACCUMULATED":86.554},"timestamp":123338},{"data":{"FLO_IPA_VALUE":0,"FLO_IPA_ACCUMULATED":18.994,"FLO_N2O_VALUE":0.52,"FLO_N2O_ACCUMULATED":86.554},"timestamp":124173},{"data":{"FLO_IPA_VALUE":0,"FLO_IPA_ACCUMULATED":18.994,"FLO_N2O_VALUE":0.552,"FLO_N2O_ACCUMULATED":87.106},"timestamp":124340},{"data":{"FLO_IPA_VALUE":0,"FLO_IPA_ACCUMULATED":18.994,"FLO_N2O_VALUE":0.552,"FLO_N2O_ACCUMULATED":87.106},"timestamp":125153},{"data":{"FLO_IPA_VALUE":0,"FLO_IPA_ACCUMULATED":18.994,"FLO_N2O_VALUE":0.536,"FLO_N2O_ACCUMULATED":87.642},"timestamp":125343},{"data":{"FLO_IPA_VALUE":0,"FLO_IPA_ACCUMULATED":18.994,"FLO_N2O_VALUE":0.536,"FLO_N2O_ACCUMULATED":87.642},"timestamp":126154},{"data":{"FLO_IPA_VALUE":0,"FLO_IPA_ACCUMULATED":18.994,"FLO_N2O_VALUE":0.496,"FLO_N2O_ACCUMULATED":88.138},"timestamp":126343},{"data":{"FLO_IPA_VALUE":0,"FLO_IPA_ACCUMULATED":18.994,"FLO_N2O_VALUE":0.496,"FLO_N2O_ACCUMULATED":88.138},"timestamp":127155},{"data":{"FLO_IPA_VALUE":0,"FLO_IPA_ACCUMULATED":18.994,"FLO_N2O_VALUE":0.522,"FLO_N2O_ACCUMULATED":88.66},"timestamp":127345},{"data":{"FLO_IPA_VALUE":0,"FLO_IPA_ACCUMULATED":18.994,"FLO_N2O_VALUE":0.522,"FLO_N2O_ACCUMULATED":88.66},"timestamp":128155},{"data":{"FLO_IPA_VALUE":0,"FLO_IPA_ACCUMULATED":18.994,"FLO_N2O_VALUE":0.507,"FLO_N2O_ACCUMULATED":89.167},"timestamp":128347},{"data":{"FLO_IPA_VALUE":0,"FLO_IPA_ACCUMULATED":18.994,"FLO_N2O_VALUE":0.507,"FLO_N2O_ACCUMULATED":89.167},"timestamp":129156},{"data":{"FLO_IPA_VALUE":0,"FLO_IPA_ACCUMULATED":18.994,"FLO_N2O_VALUE":0.499,"FLO_N2O_ACCUMULATED":89.666},"timestamp":129348},{"data":{"FLO_IPA_VALUE":0,"FLO_IPA_ACCUMULATED":18.994,"FLO_N2O_VALUE":0.499,"FLO_N2O_ACCUMULATED":89.666},"timestamp":130158},{"data":{"FLO_IPA_VALUE":0,"FLO_IPA_ACCUMULATED":18.994,"FLO_N2O_VALUE":0.507,"FLO_N2O_ACCUMULATED":90.173},"timestamp":130350},{"data":{"FLO_IPA_VALUE":0,"FLO_IPA_ACCUMULATED":18.994,"FLO_N2O_VALUE":0.507,"FLO_N2O_ACCUMULATED":90.173},"timestamp":131158},{"data":{"FLO_IPA_VALUE":0,"FLO_IPA_ACCUMULATED":18.994,"FLO_N2O_VALUE":0.484,"FLO_N2O_ACCUMULATED":90.657},"timestamp":131351},{"data":{"FLO_IPA_VALUE":0,"FLO_IPA_ACCUMULATED":18.994,"FLO_N2O_VALUE":0.484,"FLO_N2O_ACCUMULATED":90.657},"timestamp":132159},{"data":{"FLO_IPA_VALUE":0,"FLO_IPA_ACCUMULATED":18.994,"FLO_N2O_VALUE":0.545,"FLO_N2O_ACCUMULATED":91.202},"timestamp":132364},{"data":{"FLO_IPA_VALUE":0,"FLO_IPA_ACCUMULATED":18.994,"FLO_N2O_VALUE":0.545,"FLO_N2O_ACCUMULATED":91.202},"timestamp":133160},{"data":{"FLO_IPA_VALUE":0,"FLO_IPA_ACCUMULATED":18.994,"FLO_N2O_VALUE":0.558,"FLO_N2O_ACCUMULATED":91.76},"timestamp":133354},{"data":{"FLO_IPA_VALUE":0,"FLO_IPA_ACCUMULATED":18.994,"FLO_N2O_VALUE":0.558,"FLO_N2O_ACCUMULATED":91.76},"timestamp":134161},{"data":{"FLO_IPA_VALUE":0,"FLO_IPA_ACCUMULATED":18.994,"FLO_N2O_VALUE":0.612,"FLO_N2O_ACCUMULATED":92.372},"timestamp":134357},{"data":{"FLO_IPA_VALUE":0,"FLO_IPA_ACCUMULATED":18.994,"FLO_N2O_VALUE":0.612,"FLO_N2O_ACCUMULATED":92.372},"timestamp":135162},{"data":{"FLO_IPA_VALUE":0,"FLO_IPA_ACCUMULATED":18.994,"FLO_N2O_VALUE":0.605,"FLO_N2O_ACCUMULATED":92.977},"timestamp":135359},{"data":{"FLO_IPA_VALUE":0,"FLO_IPA_ACCUMULATED":18.994,"FLO_N2O_VALUE":0.605,"FLO_N2O_ACCUMULATED":92.977},"timestamp":136163},{"data":{"FLO_IPA_VALUE":0,"FLO_IPA_ACCUMULATED":18.994,"FLO_N2O_VALUE":0.545,"FLO_N2O_ACCUMULATED":93.522},"timestamp":136360},{"data":{"FLO_IPA_VALUE":0,"FLO_IPA_ACCUMULATED":18.994,"FLO_N2O_VALUE":0.545,"FLO_N2O_ACCUMULATED":93.522},"timestamp":137164},{"data":{"FLO_IPA_VALUE":0,"FLO_IPA_ACCUMULATED":18.994,"FLO_N2O_VALUE":0.493,"FLO_N2O_ACCUMULATED":94.015},"timestamp":137362},{"data":{"FLO_IPA_VALUE":0,"FLO_IPA_ACCUMULATED":18.994,"FLO_N2O_VALUE":0.493,"FLO_N2O_ACCUMULATED":94.015},"timestamp":138165},{"data":{"FLO_IPA_VALUE":0,"FLO_IPA_ACCUMULATED":18.994,"FLO_N2O_VALUE":0.476,"FLO_N2O_ACCUMULATED":94.491},"timestamp":138363},{"data":{"FLO_IPA_VALUE":0,"FLO_IPA_ACCUMULATED":18.994,"FLO_N2O_VALUE":0.476,"FLO_N2O_ACCUMULATED":94.491},"timestamp":139166},{"data":{"FLO_IPA_VALUE":0,"FLO_IPA_ACCUMULATED":18.994,"FLO_N2O_VALUE":0.499,"FLO_N2O_ACCUMULATED":94.99},"timestamp":139388},{"data":{"FLO_IPA_VALUE":0,"FLO_IPA_ACCUMULATED":18.994,"FLO_N2O_VALUE":0.499,"FLO_N2O_ACCUMULATED":94.99},"timestamp":140166},{"data":{"FLO_IPA_VALUE":0,"FLO_IPA_ACCUMULATED":18.994,"FLO_N2O_VALUE":0.51,"FLO_N2O_ACCUMULATED":95.5},"timestamp":140367},{"data":{"FLO_IPA_VALUE":0,"FLO_IPA_ACCUMULATED":18.994,"FLO_N2O_VALUE":0.51,"FLO_N2O_ACCUMULATED":95.5},"timestamp":141168},{"data":{"FLO_IPA_VALUE":0,"FLO_IPA_ACCUMULATED":18.994,"FLO_N2O_VALUE":0.52,"FLO_N2O_ACCUMULATED":96.02},"timestamp":141368},{"data":{"FLO_IPA_VALUE":0,"FLO_IPA_ACCUMULATED":18.994,"FLO_N2O_VALUE":0.52,"FLO_N2O_ACCUMULATED":96.02},"timestamp":142172},{"data":{"FLO_IPA_VALUE":0,"FLO_IPA_ACCUMULATED":18.994,"FLO_N2O_VALUE":0.53,"FLO_N2O_ACCUMULATED":96.55},"timestamp":142371},{"data":{"FLO_IPA_VALUE":0,"FLO_IPA_ACCUMULATED":18.994,"FLO_N2O_VALUE":0.53,"FLO_N2O_ACCUMULATED":96.55},"timestamp":143170},{"data":{"FLO_IPA_VALUE":0,"FLO_IPA_ACCUMULATED":18.994,"FLO_N2O_VALUE":0.587,"FLO_N2O_ACCUMULATED":97.137},"timestamp":143374},{"data":{"FLO_IPA_VALUE":0,"FLO_IPA_ACCUMULATED":18.994,"FLO_N2O_VALUE":0.587,"FLO_N2O_ACCUMULATED":97.137},"timestamp":144171},{"data":{"FLO_IPA_VALUE":0,"FLO_IPA_ACCUMULATED":18.994,"FLO_N2O_VALUE":0.552,"FLO_N2O_ACCUMULATED":97.689},"timestamp":144400},{"data":{"FLO_IPA_VALUE":0,"FLO_IPA_ACCUMULATED":18.994,"FLO_N2O_VALUE":0.552,"FLO_N2O_ACCUMULATED":97.689},"timestamp":145173},{"data":{"FLO_IPA_VALUE":0,"FLO_IPA_ACCUMULATED":18.994,"FLO_N2O_VALUE":0.555,"FLO_N2O_ACCUMULATED":98.244},"timestamp":145377},{"data":{"FLO_IPA_VALUE":0,"FLO_IPA_ACCUMULATED":18.994,"FLO_N2O_VALUE":0.555,"FLO_N2O_ACCUMULATED":98.244},"timestamp":146174},{"data":{"FLO_IPA_VALUE":0,"FLO_IPA_ACCUMULATED":18.994,"FLO_N2O_VALUE":0.554,"FLO_N2O_ACCUMULATED":98.798},"timestamp":146377},{"data":{"FLO_IPA_VALUE":0,"FLO_IPA_ACCUMULATED":18.994,"FLO_N2O_VALUE":0.554,"FLO_N2O_ACCUMULATED":98.798},"timestamp":147180},{"data":{"FLO_IPA_VALUE":0,"FLO_IPA_ACCUMULATED":18.994,"FLO_N2O_VALUE":0.533,"FLO_N2O_ACCUMULATED":99.331},"timestamp":147380},{"data":{"FLO_IPA_VALUE":0,"FLO_IPA_ACCUMULATED":18.994,"FLO_N2O_VALUE":0.533,"FLO_N2O_ACCUMULATED":99.331},"timestamp":148176},{"data":{"FLO_IPA_VALUE":0,"FLO_IPA_ACCUMULATED":18.994,"FLO_N2O_VALUE":0.473,"FLO_N2O_ACCUMULATED":99.804},"timestamp":148382},{"data":{"FLO_IPA_VALUE":0,"FLO_IPA_ACCUMULATED":18.994,"FLO_N2O_VALUE":0.473,"FLO_N2O_ACCUMULATED":99.804},"timestamp":149178},{"data":{"FLO_IPA_VALUE":0,"FLO_IPA_ACCUMULATED":18.994,"FLO_N2O_VALUE":0.508,"FLO_N2O_ACCUMULATED":100.312},"timestamp":149382},{"data":{"FLO_IPA_VALUE":0,"FLO_IPA_ACCUMULATED":18.994,"FLO_N2O_VALUE":0.508,"FLO_N2O_ACCUMULATED":100.312},"timestamp":150205},{"data":{"FLO_IPA_VALUE":0,"FLO_IPA_ACCUMULATED":18.994,"FLO_N2O_VALUE":0.555,"FLO_N2O_ACCUMULATED":100.867},"timestamp":150386},{"data":{"FLO_IPA_VALUE":0,"FLO_IPA_ACCUMULATED":18.994,"FLO_N2O_VALUE":0.555,"FLO_N2O_ACCUMULATED":100.867},"timestamp":151180},{"data":{"FLO_IPA_VALUE":0,"FLO_IPA_ACCUMULATED":18.994,"FLO_N2O_VALUE":0.534,"FLO_N2O_ACCUMULATED":101.401},"timestamp":151387},{"data":{"FLO_IPA_VALUE":0,"FLO_IPA_ACCUMULATED":18.994,"FLO_N2O_VALUE":0.534,"FLO_N2O_ACCUMULATED":101.401},"timestamp":152268},{"data":{"FLO_IPA_VALUE":0,"FLO_IPA_ACCUMULATED":18.994,"FLO_N2O_VALUE":0.523,"FLO_N2O_ACCUMULATED":101.924},"timestamp":152397},{"data":{"FLO_IPA_VALUE":0,"FLO_IPA_ACCUMULATED":18.994,"FLO_N2O_VALUE":0.523,"FLO_N2O_ACCUMULATED":101.924},"timestamp":153185},{"data":{"FLO_IPA_VALUE":0,"FLO_IPA_ACCUMULATED":18.994,"FLO_N2O_VALUE":0.54,"FLO_N2O_ACCUMULATED":102.464},"timestamp":153397},{"data":{"FLO_IPA_VALUE":0,"FLO_IPA_ACCUMULATED":18.994,"FLO_N2O_VALUE":0.54,"FLO_N2O_ACCUMULATED":102.464},"timestamp":154189},{"data":{"FLO_IPA_VALUE":0,"FLO_IPA_ACCUMULATED":18.994,"FLO_N2O_VALUE":0.525,"FLO_N2O_ACCUMULATED":102.989},"timestamp":154398},{"data":{"FLO_IPA_VALUE":0,"FLO_IPA_ACCUMULATED":18.994,"FLO_N2O_VALUE":0.525,"FLO_N2O_ACCUMULATED":102.989},"timestamp":155188},{"data":{"FLO_IPA_VALUE":0,"FLO_IPA_ACCUMULATED":18.994,"FLO_N2O_VALUE":0.519,"FLO_N2O_ACCUMULATED":103.508},"timestamp":155400},{"data":{"FLO_IPA_VALUE":0,"FLO_IPA_ACCUMULATED":18.994,"FLO_N2O_VALUE":0.519,"FLO_N2O_ACCUMULATED":103.508},"timestamp":156190},{"data":{"FLO_IPA_VALUE":0,"FLO_IPA_ACCUMULATED":18.994,"FLO_N2O_VALUE":0.546,"FLO_N2O_ACCUMULATED":104.054},"timestamp":156400},{"data":{"FLO_IPA_VALUE":0,"FLO_IPA_ACCUMULATED":18.994,"FLO_N2O_VALUE":0.546,"FLO_N2O_ACCUMULATED":104.054},"timestamp":157189},{"data":{"FLO_IPA_VALUE":0,"FLO_IPA_ACCUMULATED":18.994,"FLO_N2O_VALUE":0.49,"FLO_N2O_ACCUMULATED":104.544},"timestamp":157448},{"data":{"FLO_IPA_VALUE":0,"FLO_IPA_ACCUMULATED":18.994,"FLO_N2O_VALUE":0.49,"FLO_N2O_ACCUMULATED":104.544},"timestamp":158190},{"data":{"FLO_IPA_VALUE":0,"FLO_IPA_ACCUMULATED":18.994,"FLO_N2O_VALUE":0.493,"FLO_N2O_ACCUMULATED":105.037},"timestamp":158421},{"data":{"FLO_IPA_VALUE":0,"FLO_IPA_ACCUMULATED":18.994,"FLO_N2O_VALUE":0.493,"FLO_N2O_ACCUMULATED":105.037},"timestamp":159186},{"data":{"FLO_IPA_VALUE":0,"FLO_IPA_ACCUMULATED":18.994,"FLO_N2O_VALUE":0.511,"FLO_N2O_ACCUMULATED":105.548},"timestamp":159406},{"data":{"FLO_IPA_VALUE":0,"FLO_IPA_ACCUMULATED":18.994,"FLO_N2O_VALUE":0.511,"FLO_N2O_ACCUMULATED":105.548},"timestamp":160206},{"data":{"FLO_IPA_VALUE":0,"FLO_IPA_ACCUMULATED":18.994,"FLO_N2O_VALUE":0.49,"FLO_N2O_ACCUMULATED":106.038},"timestamp":160403},{"data":{"FLO_IPA_VALUE":0,"FLO_IPA_ACCUMULATED":18.994,"FLO_N2O_VALUE":0.49,"FLO_N2O_ACCUMULATED":106.038},"timestamp":161189},{"data":{"FLO_IPA_VALUE":0,"FLO_IPA_ACCUMULATED":18.994,"FLO_N2O_VALUE":0.495,"FLO_N2O_ACCUMULATED":106.533},"timestamp":161405},{"data":{"FLO_IPA_VALUE":0,"FLO_IPA_ACCUMULATED":18.994,"FLO_N2O_VALUE":0.495,"FLO_N2O_ACCUMULATED":106.533},"timestamp":162190},{"data":{"FLO_IPA_VALUE":0,"FLO_IPA_ACCUMULATED":18.994,"FLO_N2O_VALUE":0.572,"FLO_N2O_ACCUMULATED":107.105},"timestamp":162407},{"data":{"FLO_IPA_VALUE":0,"FLO_IPA_ACCUMULATED":18.994,"FLO_N2O_VALUE":0.572,"FLO_N2O_ACCUMULATED":107.105},"timestamp":163197},{"data":{"FLO_IPA_VALUE":0,"FLO_IPA_ACCUMULATED":18.994,"FLO_N2O_VALUE":0.561,"FLO_N2O_ACCUMULATED":107.666},"timestamp":163412},{"data":{"FLO_IPA_VALUE":0,"FLO_IPA_ACCUMULATED":18.994,"FLO_N2O_VALUE":0.561,"FLO_N2O_ACCUMULATED":107.666},"timestamp":164198},{"data":{"FLO_IPA_VALUE":0,"FLO_IPA_ACCUMULATED":18.994,"FLO_N2O_VALUE":0.461,"FLO_N2O_ACCUMULATED":108.127},"timestamp":164413},{"data":{"FLO_IPA_VALUE":0,"FLO_IPA_ACCUMULATED":18.994,"FLO_N2O_VALUE":0.461,"FLO_N2O_ACCUMULATED":108.127},"timestamp":165195},{"data":{"FLO_IPA_VALUE":0,"FLO_IPA_ACCUMULATED":18.994,"FLO_N2O_VALUE":0.548,"FLO_N2O_ACCUMULATED":108.675},"timestamp":165414},{"data":{"FLO_IPA_VALUE":0,"FLO_IPA_ACCUMULATED":18.994,"FLO_N2O_VALUE":0.548,"FLO_N2O_ACCUMULATED":108.675},"timestamp":166199},{"data":{"FLO_IPA_VALUE":0,"FLO_IPA_ACCUMULATED":18.994,"FLO_N2O_VALUE":0.536,"FLO_N2O_ACCUMULATED":109.211},"timestamp":166413},{"data":{"FLO_IPA_VALUE":0,"FLO_IPA_ACCUMULATED":18.994,"FLO_N2O_VALUE":0.536,"FLO_N2O_ACCUMULATED":109.211},"timestamp":167196},{"data":{"FLO_IPA_VALUE":0,"FLO_IPA_ACCUMULATED":18.994,"FLO_N2O_VALUE":0.484,"FLO_N2O_ACCUMULATED":109.695},"timestamp":167414},{"data":{"FLO_IPA_VALUE":0,"FLO_IPA_ACCUMULATED":18.994,"FLO_N2O_VALUE":0.484,"FLO_N2O_ACCUMULATED":109.695},"timestamp":168259},{"data":{"FLO_IPA_VALUE":0,"FLO_IPA_ACCUMULATED":18.994,"FLO_N2O_VALUE":0.525,"FLO_N2O_ACCUMULATED":110.22},"timestamp":168417},{"data":{"FLO_IPA_VALUE":0,"FLO_IPA_ACCUMULATED":18.994,"FLO_N2O_VALUE":0.525,"FLO_N2O_ACCUMULATED":110.22},"timestamp":169197},{"data":{"FLO_IPA_VALUE":0,"FLO_IPA_ACCUMULATED":18.994,"FLO_N2O_VALUE":0.549,"FLO_N2O_ACCUMULATED":110.769},"timestamp":169419},{"data":{"FLO_IPA_VALUE":0,"FLO_IPA_ACCUMULATED":18.994,"FLO_N2O_VALUE":0.549,"FLO_N2O_ACCUMULATED":110.769},"timestamp":170199},{"data":{"FLO_IPA_VALUE":0,"FLO_IPA_ACCUMULATED":18.994,"FLO_N2O_VALUE":0.554,"FLO_N2O_ACCUMULATED":111.323},"timestamp":170421},{"data":{"FLO_IPA_VALUE":0,"FLO_IPA_ACCUMULATED":18.994,"FLO_N2O_VALUE":0.554,"FLO_N2O_ACCUMULATED":111.323},"timestamp":171200},{"data":{"FLO_IPA_VALUE":0,"FLO_IPA_ACCUMULATED":18.994,"FLO_N2O_VALUE":0.592,"FLO_N2O_ACCUMULATED":111.915},"timestamp":171421},{"data":{"FLO_IPA_VALUE":0,"FLO_IPA_ACCUMULATED":18.994,"FLO_N2O_VALUE":0.592,"FLO_N2O_ACCUMULATED":111.915},"timestamp":172200},{"data":{"FLO_IPA_VALUE":0,"FLO_IPA_ACCUMULATED":18.994,"FLO_N2O_VALUE":0.498,"FLO_N2O_ACCUMULATED":112.413},"timestamp":172428},{"data":{"FLO_IPA_VALUE":0,"FLO_IPA_ACCUMULATED":18.994,"FLO_N2O_VALUE":0.498,"FLO_N2O_ACCUMULATED":112.413},"timestamp":173201},{"data":{"FLO_IPA_VALUE":0,"FLO_IPA_ACCUMULATED":18.994,"FLO_N2O_VALUE":0.569,"FLO_N2O_ACCUMULATED":112.982},"timestamp":173427},{"data":{"FLO_IPA_VALUE":0,"FLO_IPA_ACCUMULATED":18.994,"FLO_N2O_VALUE":0.569,"FLO_N2O_ACCUMULATED":112.982},"timestamp":174202},{"data":{"FLO_IPA_VALUE":0,"FLO_IPA_ACCUMULATED":18.994,"FLO_N2O_VALUE":0.566,"FLO_N2O_ACCUMULATED":113.548},"timestamp":174425},{"data":{"FLO_IPA_VALUE":0,"FLO_IPA_ACCUMULATED":18.994,"FLO_N2O_VALUE":0.566,"FLO_N2O_ACCUMULATED":113.548},"timestamp":175203},{"data":{"FLO_IPA_VALUE":0,"FLO_IPA_ACCUMULATED":18.994,"FLO_N2O_VALUE":0.564,"FLO_N2O_ACCUMULATED":114.112},"timestamp":175428},{"data":{"FLO_IPA_VALUE":0,"FLO_IPA_ACCUMULATED":18.994,"FLO_N2O_VALUE":0.564,"FLO_N2O_ACCUMULATED":114.112},"timestamp":176204},{"data":{"FLO_IPA_VALUE":0,"FLO_IPA_ACCUMULATED":18.994,"FLO_N2O_VALUE":0.464,"FLO_N2O_ACCUMULATED":114.576},"timestamp":176434},{"data":{"FLO_IPA_VALUE":0,"FLO_IPA_ACCUMULATED":18.994,"FLO_N2O_VALUE":0.464,"FLO_N2O_ACCUMULATED":114.576},"timestamp":177204},{"data":{"FLO_IPA_VALUE":0,"FLO_IPA_ACCUMULATED":18.994,"FLO_N2O_VALUE":0.557,"FLO_N2O_ACCUMULATED":115.133},"timestamp":177430},{"data":{"FLO_IPA_VALUE":0,"FLO_IPA_ACCUMULATED":18.994,"FLO_N2O_VALUE":0.557,"FLO_N2O_ACCUMULATED":115.133},"timestamp":178206},{"data":{"FLO_IPA_VALUE":0,"FLO_IPA_ACCUMULATED":18.994,"FLO_N2O_VALUE":0.513,"FLO_N2O_ACCUMULATED":115.646},"timestamp":178450},{"data":{"FLO_IPA_VALUE":0,"FLO_IPA_ACCUMULATED":18.994,"FLO_N2O_VALUE":0.513,"FLO_N2O_ACCUMULATED":115.646},"timestamp":179206},{"data":{"FLO_IPA_VALUE":0,"FLO_IPA_ACCUMULATED":18.994,"FLO_N2O_VALUE":0.496,"FLO_N2O_ACCUMULATED":116.142},"timestamp":179433},{"data":{"FLO_IPA_VALUE":0,"FLO_IPA_ACCUMULATED":18.994,"FLO_N2O_VALUE":0.496,"FLO_N2O_ACCUMULATED":116.142},"timestamp":180221},{"data":{"FLO_IPA_VALUE":0,"FLO_IPA_ACCUMULATED":18.994,"FLO_N2O_VALUE":0.526,"FLO_N2O_ACCUMULATED":116.668},"timestamp":180436},{"data":{"FLO_IPA_VALUE":0,"FLO_IPA_ACCUMULATED":18.994,"FLO_N2O_VALUE":0.526,"FLO_N2O_ACCUMULATED":116.668},"timestamp":181208},{"data":{"FLO_IPA_VALUE":0,"FLO_IPA_ACCUMULATED":18.994,"FLO_N2O_VALUE":0.53,"FLO_N2O_ACCUMULATED":117.198},"timestamp":181436},{"data":{"FLO_IPA_VALUE":0,"FLO_IPA_ACCUMULATED":18.994,"FLO_N2O_VALUE":0.53,"FLO_N2O_ACCUMULATED":117.198},"timestamp":182209},{"data":{"FLO_IPA_VALUE":0,"FLO_IPA_ACCUMULATED":18.994,"FLO_N2O_VALUE":0.522,"FLO_N2O_ACCUMULATED":117.72},"timestamp":182438},{"data":{"FLO_IPA_VALUE":0,"FLO_IPA_ACCUMULATED":18.994,"FLO_N2O_VALUE":0.522,"FLO_N2O_ACCUMULATED":117.72},"timestamp":183209},{"data":{"FLO_IPA_VALUE":0,"FLO_IPA_ACCUMULATED":18.994,"FLO_N2O_VALUE":0.572,"FLO_N2O_ACCUMULATED":118.292},"timestamp":183440},{"data":{"FLO_IPA_VALUE":0,"FLO_IPA_ACCUMULATED":18.994,"FLO_N2O_VALUE":0.572,"FLO_N2O_ACCUMULATED":118.292},"timestamp":184211},{"data":{"FLO_IPA_VALUE":0,"FLO_IPA_ACCUMULATED":18.994,"FLO_N2O_VALUE":0.476,"FLO_N2O_ACCUMULATED":118.768},"timestamp":184442},{"data":{"FLO_IPA_VALUE":0,"FLO_IPA_ACCUMULATED":18.994,"FLO_N2O_VALUE":0.476,"FLO_N2O_ACCUMULATED":118.768},"timestamp":185215},{"data":{"FLO_IPA_VALUE":0,"FLO_IPA_ACCUMULATED":18.994,"FLO_N2O_VALUE":0.511,"FLO_N2O_ACCUMULATED":119.279},"timestamp":185444},{"data":{"FLO_IPA_VALUE":0,"FLO_IPA_ACCUMULATED":18.994,"FLO_N2O_VALUE":0.511,"FLO_N2O_ACCUMULATED":119.279},"timestamp":186212},{"data":{"FLO_IPA_VALUE":0,"FLO_IPA_ACCUMULATED":18.994,"FLO_N2O_VALUE":0.479,"FLO_N2O_ACCUMULATED":119.758},"timestamp":186450},{"data":{"FLO_IPA_VALUE":0,"FLO_IPA_ACCUMULATED":18.994,"FLO_N2O_VALUE":0.479,"FLO_N2O_ACCUMULATED":119.758},"timestamp":187212},{"data":{"FLO_IPA_VALUE":0,"FLO_IPA_ACCUMULATED":18.994,"FLO_N2O_VALUE":0.501,"FLO_N2O_ACCUMULATED":120.259},"timestamp":187456},{"data":{"FLO_IPA_VALUE":0,"FLO_IPA_ACCUMULATED":18.994,"FLO_N2O_VALUE":0.501,"FLO_N2O_ACCUMULATED":120.259},"timestamp":188215},{"data":{"FLO_IPA_VALUE":0,"FLO_IPA_ACCUMULATED":18.994,"FLO_N2O_VALUE":0.539,"FLO_N2O_ACCUMULATED":120.798},"timestamp":188448},{"data":{"FLO_IPA_VALUE":0,"FLO_IPA_ACCUMULATED":18.994,"FLO_N2O_VALUE":0.539,"FLO_N2O_ACCUMULATED":120.798},"timestamp":189216},{"data":{"FLO_IPA_VALUE":0,"FLO_IPA_ACCUMULATED":18.994,"FLO_N2O_VALUE":0.513,"FLO_N2O_ACCUMULATED":121.311},"timestamp":189450},{"data":{"FLO_IPA_VALUE":0,"FLO_IPA_ACCUMULATED":18.994,"FLO_N2O_VALUE":0.513,"FLO_N2O_ACCUMULATED":121.311},"timestamp":190236},{"data":{"FLO_IPA_VALUE":0,"FLO_IPA_ACCUMULATED":18.994,"FLO_N2O_VALUE":0.513,"FLO_N2O_ACCUMULATED":121.824},"timestamp":190470},{"data":{"FLO_IPA_VALUE":0,"FLO_IPA_ACCUMULATED":18.994,"FLO_N2O_VALUE":0.513,"FLO_N2O_ACCUMULATED":121.824},"timestamp":191219},{"data":{"FLO_IPA_VALUE":0,"FLO_IPA_ACCUMULATED":18.994,"FLO_N2O_VALUE":0.539,"FLO_N2O_ACCUMULATED":122.363},"timestamp":191453},{"data":{"FLO_IPA_VALUE":0,"FLO_IPA_ACCUMULATED":18.994,"FLO_N2O_VALUE":0.539,"FLO_N2O_ACCUMULATED":122.363},"timestamp":192219},{"data":{"FLO_IPA_VALUE":0,"FLO_IPA_ACCUMULATED":18.994,"FLO_N2O_VALUE":0.481,"FLO_N2O_ACCUMULATED":122.844},"timestamp":192454},{"data":{"FLO_IPA_VALUE":0,"FLO_IPA_ACCUMULATED":18.994,"FLO_N2O_VALUE":0.481,"FLO_N2O_ACCUMULATED":122.844},"timestamp":193220},{"data":{"FLO_IPA_VALUE":0,"FLO_IPA_ACCUMULATED":18.994,"FLO_N2O_VALUE":0.511,"FLO_N2O_ACCUMULATED":123.355},"timestamp":193456},{"data":{"FLO_IPA_VALUE":0,"FLO_IPA_ACCUMULATED":18.994,"FLO_N2O_VALUE":0.511,"FLO_N2O_ACCUMULATED":123.355},"timestamp":194220},{"data":{"FLO_IPA_VALUE":0,"FLO_IPA_ACCUMULATED":18.994,"FLO_N2O_VALUE":0.484,"FLO_N2O_ACCUMULATED":123.839},"timestamp":194458},{"data":{"FLO_IPA_VALUE":0,"FLO_IPA_ACCUMULATED":18.994,"FLO_N2O_VALUE":0.484,"FLO_N2O_ACCUMULATED":123.839},"timestamp":195244},{"data":{"FLO_IPA_VALUE":0,"FLO_IPA_ACCUMULATED":18.994,"FLO_N2O_VALUE":0.337,"FLO_N2O_ACCUMULATED":124.176},"timestamp":195460},{"data":{"FLO_IPA_VALUE":0,"FLO_IPA_ACCUMULATED":18.994,"FLO_N2O_VALUE":0.337,"FLO_N2O_ACCUMULATED":124.176},"timestamp":196222},{"data":{"FLO_IPA_VALUE":0,"FLO_IPA_ACCUMULATED":18.994,"FLO_N2O_VALUE":0,"FLO_N2O_ACCUMULATED":124.176},"timestamp":196461},{"data":{"FLO_IPA_VALUE":0,"FLO_IPA_ACCUMULATED":18.994,"FLO_N2O_VALUE":0,"FLO_N2O_ACCUMULATED":124.176},"timestamp":197223},{"data":{"FLO_IPA_VALUE":0,"FLO_IPA_ACCUMULATED":18.994,"FLO_N2O_VALUE":0,"FLO_N2O_ACCUMULATED":124.176},"timestamp":197463}],"PRESSURE":[{"data":{"PT_IPA":6.289460000000001,"PT_N2O":-0.08107266666666667,"PT_CHAM":0.0045,"PT_N2":100.95152000000002,"PT_FUEL":1529.272896,"PT_OX":1528.8900599999997},"timestamp":246},{"data":{"PT_IPA":6.289460000000001,"PT_N2O":-0.10438633333333333,"PT_CHAM":0.0045,"PT_N2":100.95152000000002,"PT_FUEL":1529.272896,"PT_OX":1528.8900599999997},"timestamp":1269},{"data":{"PT_IPA":6.289460000000001,"PT_N2O":-0.10438633333333333,"PT_CHAM":0.0045,"PT_N2":100.95152000000002,"PT_FUEL":1529.272896,"PT_OX":1528.8900599999997},"timestamp":3317},{"data":{"PT_IPA":6.289460000000001,"PT_N2O":-0.08107266666666667,"PT_CHAM":0.0045,"PT_N2":101.1852,"PT_FUEL":1529.272896,"PT_OX":1528.8900599999997},"timestamp":4341},{"data":{"PT_IPA":6.289460000000001,"PT_N2O":-0.10438633333333333,"PT_CHAM":0.0045,"PT_N2":100.95152000000002,"PT_FUEL":1529.272896,"PT_OX":1528.8900599999997},"timestamp":5365},{"data":{"PT_IPA":6.289460000000001,"PT_N2O":-0.10438633333333333,"PT_CHAM":0.0045,"PT_N2":100.71784000000001,"PT_FUEL":1529.272896,"PT_OX":1528.8900599999997},"timestamp":6389},{"data":{"PT_IPA":6.289460000000001,"PT_N2O":-0.08107266666666667,"PT_CHAM":0.0045,"PT_N2":100.71784000000001,"PT_FUEL":1529.272896,"PT_OX":1528.8900599999997},"timestamp":7413},{"data":{"PT_IPA":6.289460000000001,"PT_N2O":-0.10438633333333333,"PT_CHAM":0.0045,"PT_N2":100.0168,"PT_FUEL":1529.2495596666668,"PT_OX":1528.8900599999997},"timestamp":8437},{"data":{"PT_IPA":6.289460000000001,"PT_N2O":-0.10438633333333333,"PT_CHAM":0.0045,"PT_N2":99.31576,"PT_FUEL":1529.272896,"PT_OX":1528.8900599999997},"timestamp":9461},{"data":{"PT_IPA":6.289460000000001,"PT_N2O":-0.08107266666666667,"PT_CHAM":0.0045,"PT_N2":99.08208,"PT_FUEL":1529.2495596666668,"PT_OX":1528.8900599999997},"timestamp":10485},{"data":{"PT_IPA":6.289460000000001,"PT_N2O":-0.08107266666666667,"PT_CHAM":0.0045,"PT_N2":98.61472,"PT_FUEL":1529.2495596666668,"PT_OX":1528.8900599999997},"timestamp":11509},{"data":{"PT_IPA":6.289460000000001,"PT_N2O":-0.10438633333333333,"PT_CHAM":0.0045,"PT_N2":98.14736,"PT_FUEL":1529.272896,"PT_OX":1528.8900599999997},"timestamp":12534},{"data":{"PT_IPA":6.289460000000001,"PT_N2O":-0.08107266666666667,"PT_CHAM":0.0045,"PT_N2":97.44632000000001,"PT_FUEL":1529.272896,"PT_OX":1528.8900599999997},"timestamp":13557},{"data":{"PT_IPA":6.289460000000001,"PT_N2O":-0.08107266666666667,"PT_CHAM":0.0045,"PT_N2":96.74528000000002,"PT_FUEL":1529.2495596666668,"PT_OX":1528.8900599999997},"timestamp":14588},{"data":{"PT_IPA":6.289460000000001,"PT_N2O":-0.08107266666666667,"PT_CHAM":0.0045,"PT_N2":96.04424000000002,"PT_FUEL":1529.2495596666668,"PT_OX":1528.8900599999997},"timestamp":15606},{"data":{"PT_IPA":6.289460000000001,"PT_N2O":-0.08107266666666667,"PT_CHAM":0.0045,"PT_N2":95.57688000000002,"PT_FUEL":1529.2495596666668,"PT_OX":1528.8900599999997},"timestamp":16629},{"data":{"PT_IPA":6.289460000000001,"PT_N2O":-0.08107266666666667,"PT_CHAM":0.0045,"PT_N2":94.87584000000001,"PT_FUEL":1529.2495596666668,"PT_OX":1528.8900599999997},"timestamp":17654},{"data":{"PT_IPA":6.289460000000001,"PT_N2O":-0.08107266666666667,"PT_CHAM":0.0045,"PT_N2":94.40848000000001,"PT_FUEL":1529.2495596666668,"PT_OX":1528.8900599999997},"timestamp":18678},{"data":{"PT_IPA":6.289460000000001,"PT_N2O":-0.10438633333333333,"PT_CHAM":0.0045,"PT_N2":93.70744000000002,"PT_FUEL":1529.2495596666668,"PT_OX":1528.8900599999997},"timestamp":19702},{"data":{"PT_IPA":6.289460000000001,"PT_N2O":-0.08107266666666667,"PT_CHAM":0.0045,"PT_N2":93.24008000000002,"PT_FUEL":1529.2495596666668,"PT_OX":1528.8900599999997},"timestamp":20726},{"data":{"PT_IPA":6.289460000000001,"PT_N2O":-0.10438633333333333,"PT_CHAM":0.0045,"PT_N2":92.53904000000001,"PT_FUEL":1529.272896,"PT_OX":1528.8900599999997},"timestamp":21750},{"data":{"PT_IPA":6.289460000000001,"PT_N2O":-0.08107266666666667,"PT_CHAM":0.0045,"PT_N2":92.07168000000001,"PT_FUEL":1529.272896,"PT_OX":1528.8900599999997},"timestamp":22774},{"data":{"PT_IPA":6.289460000000001,"PT_N2O":-0.10438633333333333,"PT_CHAM":0.0045,"PT_N2":91.13696000000002,"PT_FUEL":1529.272896,"PT_OX":1528.8900599999997},"timestamp":24847},{"data":{"PT_IPA":6.289460000000001,"PT_N2O":-0.08107266666666667,"PT_CHAM":0.0045,"PT_N2":91.13696000000002,"PT_FUEL":1529.272896,"PT_OX":1528.8900599999997},"timestamp":25847},{"data":{"PT_IPA":6.289460000000001,"PT_N2O":-0.10438633333333333,"PT_CHAM":0.0045,"PT_N2":91.13696000000002,"PT_FUEL":1529.272896,"PT_OX":1528.8900599999997},"timestamp":26870},{"data":{"PT_IPA":6.289460000000001,"PT_N2O":-0.10438633333333333,"PT_CHAM":0.0045,"PT_N2":91.13696000000002,"PT_FUEL":1529.2495596666668,"PT_OX":1528.8900599999997},"timestamp":27895},{"data":{"PT_IPA":6.289460000000001,"PT_N2O":-0.08107266666666667,"PT_CHAM":0.0045,"PT_N2":90.90328000000001,"PT_FUEL":1529.272896,"PT_OX":1528.8900599999997},"timestamp":28918},{"data":{"PT_IPA":6.289460000000001,"PT_N2O":-0.10438633333333333,"PT_CHAM":0.0045,"PT_N2":90.43592000000002,"PT_FUEL":1529.272896,"PT_OX":1528.8900599999997},"timestamp":29942},{"data":{"PT_IPA":6.289460000000001,"PT_N2O":-0.08107266666666667,"PT_CHAM":0.0045,"PT_N2":89.96856000000001,"PT_FUEL":1529.2495596666668,"PT_OX":1528.8900599999997},"timestamp":30966},{"data":{"PT_IPA":6.289460000000001,"PT_N2O":-0.08107266666666667,"PT_CHAM":0.0045,"PT_N2":89.50120000000001,"PT_FUEL":1529.272896,"PT_OX":1528.8900599999997},"timestamp":31990},{"data":{"PT_IPA":6.289460000000001,"PT_N2O":-0.08107266666666667,"PT_CHAM":0.0045,"PT_N2":88.80016,"PT_FUEL":1529.2495596666668,"PT_OX":1528.8900599999997},"timestamp":33014},{"data":{"PT_IPA":6.289460000000001,"PT_N2O":-0.10438633333333333,"PT_CHAM":0.0045,"PT_N2":88.33280000000002,"PT_FUEL":1529.2495596666668,"PT_OX":1528.8900599999997},"timestamp":34039},{"data":{"PT_IPA":6.289460000000001,"PT_N2O":-0.08107266666666667,"PT_CHAM":0.0045,"PT_N2":87.86544,"PT_FUEL":1529.2495596666668,"PT_OX":1528.8900599999997},"timestamp":35063},{"data":{"PT_IPA":6.289460000000001,"PT_N2O":-0.10438633333333333,"PT_CHAM":0.0045,"PT_N2":87.1644,"PT_FUEL":1529.2495596666668,"PT_OX":1528.8900599999997},"timestamp":36093},{"data":{"PT_IPA":6.289460000000001,"PT_N2O":-0.08107266666666667,"PT_CHAM":0.0045,"PT_N2":86.69704000000002,"PT_FUEL":1529.272896,"PT_OX":1528.8900599999997},"timestamp":37110},{"data":{"PT_IPA":6.289460000000001,"PT_N2O":-0.08107266666666667,"PT_CHAM":0.0045,"PT_N2":85.99600000000001,"PT_FUEL":1529.2495596666668,"PT_OX":1528.8900599999997},"timestamp":38135},{"data":{"PT_IPA":6.289460000000001,"PT_N2O":-0.08107266666666667,"PT_CHAM":0.0045,"PT_N2":85.52864000000001,"PT_FUEL":1529.272896,"PT_OX":1528.8900599999997},"timestamp":39158},{"data":{"PT_IPA":6.289460000000001,"PT_N2O":-0.10438633333333333,"PT_CHAM":0.0045,"PT_N2":85.06128,"PT_FUEL":1529.272896,"PT_OX":1528.8900599999997},"timestamp":40195},{"data":{"PT_IPA":6.289460000000001,"PT_N2O":-0.10438633333333333,"PT_CHAM":0.0045,"PT_N2":84.59392000000001,"PT_FUEL":1529.2495596666668,"PT_OX":1528.8900599999997},"timestamp":41224},{"data":{"PT_IPA":6.289460000000001,"PT_N2O":-0.08107266666666667,"PT_CHAM":0.0045,"PT_N2":83.89288,"PT_FUEL":1529.272896,"PT_OX":1528.8900599999997},"timestamp":42230},{"data":{"PT_IPA":6.289460000000001,"PT_N2O":-0.10438633333333333,"PT_CHAM":0.0045,"PT_N2":83.42552,"PT_FUEL":1529.272896,"PT_OX":1528.8900599999997},"timestamp":43254},{"data":{"PT_IPA":6.289460000000001,"PT_N2O":-0.10438633333333333,"PT_CHAM":0.0045,"PT_N2":82.95816,"PT_FUEL":1529.272896,"PT_OX":1528.8900599999997},"timestamp":44278},{"data":{"PT_IPA":6.289460000000001,"PT_N2O":-0.10438633333333333,"PT_CHAM":0.0045,"PT_N2":82.02344000000001,"PT_FUEL":1529.2495596666668,"PT_OX":1528.8900599999997},"timestamp":46326},{"data":{"PT_IPA":6.289460000000001,"PT_N2O":-0.08107266666666667,"PT_CHAM":0.0045,"PT_N2":81.32240000000002,"PT_FUEL":1529.2495596666668,"PT_OX":1528.8900599999997},"timestamp":47350},{"data":{"PT_IPA":6.289460000000001,"PT_N2O":-0.08107266666666667,"PT_CHAM":0.0045,"PT_N2":80.85504000000002,"PT_FUEL":1529.2495596666668,"PT_OX":1528.8900599999997},"timestamp":48374},{"data":{"PT_IPA":6.289460000000001,"PT_N2O":-0.08107266666666667,"PT_CHAM":0.0045,"PT_N2":79.92032,"PT_FUEL":1529.272896,"PT_OX":1528.8900599999997},"timestamp":50422},{"data":{"PT_IPA":6.289460000000001,"PT_N2O":-0.08107266666666667,"PT_CHAM":0.0045,"PT_N2":79.68664000000001,"PT_FUEL":1529.2495596666668,"PT_OX":1528.8900599999997},"timestamp":51474},{"data":{"PT_IPA":6.289460000000001,"PT_N2O":-0.08107266666666667,"PT_CHAM":0.0045,"PT_N2":80.15400000000001,"PT_FUEL":1529.272896,"PT_OX":1528.8900599999997},"timestamp":53521},{"data":{"PT_IPA":6.289460000000001,"PT_N2O":-0.10438633333333333,"PT_CHAM":0.0045,"PT_N2":79.92032,"PT_FUEL":1529.272896,"PT_OX":1528.8900599999997},"timestamp":54518},{"data":{"PT_IPA":6.289460000000001,"PT_N2O":-0.08107266666666667,"PT_CHAM":0.0045,"PT_N2":74.77936000000001,"PT_FUEL":1529.272896,"PT_OX":1528.8900599999997},"timestamp":56567},{"data":{"PT_IPA":6.289460000000001,"PT_N2O":-0.10438633333333333,"PT_CHAM":0.0045,"PT_N2":72.67624,"PT_FUEL":1529.272896,"PT_OX":1528.8900599999997},"timestamp":57619},{"data":{"PT_IPA":6.289460000000001,"PT_N2O":-0.08107266666666667,"PT_CHAM":0.0045,"PT_N2":67.30160000000001,"PT_FUEL":1529.272896,"PT_OX":1528.8900599999997},"timestamp":59641},{"data":{"PT_IPA":6.289460000000001,"PT_N2O":-0.10438633333333333,"PT_CHAM":0.0045,"PT_N2":64.73112000000002,"PT_FUEL":1529.2495596666668,"PT_OX":1528.8900599999997},"timestamp":60664},{"data":{"PT_IPA":6.289460000000001,"PT_N2O":-0.10438633333333333,"PT_CHAM":0.0045,"PT_N2":60.291199999999996,"PT_FUEL":1529.272896,"PT_OX":1528.8900599999997},"timestamp":62711},{"data":{"PT_IPA":6.289460000000001,"PT_N2O":-0.10438633333333333,"PT_CHAM":0.0045,"PT_N2":58.65544,"PT_FUEL":1529.272896,"PT_OX":1528.8900599999997},"timestamp":63765},{"data":{"PT_IPA":6.289460000000001,"PT_N2O":-0.08107266666666667,"PT_CHAM":0.0045,"PT_N2":55.6176,"PT_FUEL":1529.272896,"PT_OX":1528.8900599999997},"timestamp":65784},{"data":{"PT_IPA":6.289460000000001,"PT_N2O":-0.08107266666666667,"PT_CHAM":0.0045,"PT_N2":53.04712000000001,"PT_FUEL":1529.272896,"PT_OX":1528.8900599999997},"timestamp":67832},{"data":{"PT_IPA":6.289460000000001,"PT_N2O":-0.10438633333333333,"PT_CHAM":0.0045,"PT_N2":51.17768,"PT_FUEL":1529.2495596666668,"PT_OX":1528.8900599999997},"timestamp":68856},{"data":{"PT_IPA":6.289460000000001,"PT_N2O":-0.10438633333333333,"PT_CHAM":0.0045,"PT_N2":49.54192,"PT_FUEL":1529.272896,"PT_OX":1528.8900599999997},"timestamp":69908},{"data":{"PT_IPA":6.289460000000001,"PT_N2O":-0.08107266666666667,"PT_CHAM":0.0045,"PT_N2":47.90616,"PT_FUEL":1529.2495596666668,"PT_OX":1528.8900599999997},"timestamp":70911},{"data":{"PT_IPA":6.289460000000001,"PT_N2O":-0.08107266666666667,"PT_CHAM":0.0045,"PT_N2":46.2704,"PT_FUEL":1529.272896,"PT_OX":1528.8900599999997},"timestamp":71928},{"data":{"PT_IPA":6.289460000000001,"PT_N2O":-0.08107266666666667,"PT_CHAM":0.0045,"PT_N2":44.634640000000005,"PT_FUEL":1529.2495596666668,"PT_OX":1528.8900599999997},"timestamp":72951},{"data":{"PT_IPA":6.289460000000001,"PT_N2O":-0.08107266666666667,"PT_CHAM":0.0045,"PT_N2":43.23256,"PT_FUEL":1529.2495596666668,"PT_OX":1528.8900599999997},"timestamp":73976},{"data":{"PT_IPA":6.289460000000001,"PT_N2O":-0.08107266666666667,"PT_CHAM":0.0045,"PT_N2":41.83048,"PT_FUEL":1529.2495596666668,"PT_OX":1528.8900599999997},"timestamp":75031},{"data":{"PT_IPA":6.289460000000001,"PT_N2O":-0.10438633333333333,"PT_CHAM":0.0045,"PT_N2":40.4284,"PT_FUEL":1529.272896,"PT_OX":1528.8900599999997},"timestamp":76023},{"data":{"PT_IPA":6.289460000000001,"PT_N2O":-0.10438633333333333,"PT_CHAM":0.0045,"PT_N2":39.260000000000005,"PT_FUEL":1529.272896,"PT_OX":1528.8900599999997},"timestamp":77049},{"data":{"PT_IPA":6.289460000000001,"PT_N2O":-0.08107266666666667,"PT_CHAM":0.0045,"PT_N2":37.85792,"PT_FUEL":1529.272896,"PT_OX":1528.8900599999997},"timestamp":78072},{"data":{"PT_IPA":6.289460000000001,"PT_N2O":-0.08107266666666667,"PT_CHAM":0.0045,"PT_N2":36.68952,"PT_FUEL":1529.2495596666668,"PT_OX":1528.8900599999997},"timestamp":79096},{"data":{"PT_IPA":6.289460000000001,"PT_N2O":-0.08107266666666667,"PT_CHAM":0.0045,"PT_N2":35.521119999999996,"PT_FUEL":1529.2495596666668,"PT_OX":1528.8900599999997},"timestamp":80166},{"data":{"PT_IPA":6.289460000000001,"PT_N2O":-0.08107266666666667,"PT_CHAM":0.0045,"PT_N2":34.35272,"PT_FUEL":1529.272896,"PT_OX":1528.8900599999997},"timestamp":81143},{"data":{"PT_IPA":6.289460000000001,"PT_N2O":-0.08107266666666667,"PT_CHAM":0.0045,"PT_N2":33.418,"PT_FUEL":1529.2495596666668,"PT_OX":1528.8900599999997},"timestamp":82167},{"data":{"PT_IPA":6.289460000000001,"PT_N2O":-0.08107266666666667,"PT_CHAM":0.0045,"PT_N2":32.2496,"PT_FUEL":1529.272896,"PT_OX":1528.8900599999997},"timestamp":83192},{"data":{"PT_IPA":6.289460000000001,"PT_N2O":-0.10438633333333333,"PT_CHAM":0.0045,"PT_N2":31.314880000000002,"PT_FUEL":1529.272896,"PT_OX":1528.8900599999997},"timestamp":84217},{"data":{"PT_IPA":6.289460000000001,"PT_N2O":-0.08107266666666667,"PT_CHAM":0.0045,"PT_N2":30.146480000000004,"PT_FUEL":1529.272896,"PT_OX":1528.8900599999997},"timestamp":85272},{"data":{"PT_IPA":6.289460000000001,"PT_N2O":-0.08107266666666667,"PT_CHAM":0.0045,"PT_N2":29.21176,"PT_FUEL":1529.272896,"PT_OX":1528.8900599999997},"timestamp":86264},{"data":{"PT_IPA":6.289460000000001,"PT_N2O":-0.10438633333333333,"PT_CHAM":0.0045,"PT_N2":28.277040000000003,"PT_FUEL":1529.2495596666668,"PT_OX":1528.8900599999997},"timestamp":87304},{"data":{"PT_IPA":6.289460000000001,"PT_N2O":-0.08107266666666667,"PT_CHAM":0.0045,"PT_N2":27.342320000000004,"PT_FUEL":1529.2495596666668,"PT_OX":1528.8900599999997},"timestamp":88311},{"data":{"PT_IPA":6.289460000000001,"PT_N2O":-0.08107266666666667,"PT_CHAM":0.0045,"PT_N2":26.641280000000005,"PT_FUEL":1529.272896,"PT_OX":1528.8900599999997},"timestamp":89336},{"data":{"PT_IPA":6.289460000000001,"PT_N2O":-0.10438633333333333,"PT_CHAM":0.0045,"PT_N2":25.706560000000003,"PT_FUEL":1529.272896,"PT_OX":1528.8900599999997},"timestamp":90392},{"data":{"PT_IPA":6.289460000000001,"PT_N2O":-0.10438633333333333,"PT_CHAM":0.0045,"PT_N2":24.77184,"PT_FUEL":1529.2495596666668,"PT_OX":1528.8900599999997},"timestamp":91385},{"data":{"PT_IPA":6.289460000000001,"PT_N2O":-0.10438633333333333,"PT_CHAM":0.0045,"PT_N2":24.0708,"PT_FUEL":1529.272896,"PT_OX":1528.8900599999997},"timestamp":92408},{"data":{"PT_IPA":6.289460000000001,"PT_N2O":-0.08107266666666667,"PT_CHAM":0.0045,"PT_N2":23.136080000000007,"PT_FUEL":1529.272896,"PT_OX":1528.8900599999997},"timestamp":93433},{"data":{"PT_IPA":6.289460000000001,"PT_N2O":-0.10438633333333333,"PT_CHAM":0.0045,"PT_N2":22.435040000000004,"PT_FUEL":1529.272896,"PT_OX":1528.8900599999997},"timestamp":94457},{"data":{"PT_IPA":6.289460000000001,"PT_N2O":-0.08107266666666667,"PT_CHAM":0.0045,"PT_N2":21.734000000000005,"PT_FUEL":1529.272896,"PT_OX":1528.8900599999997},"timestamp":95537},{"data":{"PT_IPA":6.289460000000001,"PT_N2O":-0.08107266666666667,"PT_CHAM":0.0045,"PT_N2":21.032960000000003,"PT_FUEL":1529.272896,"PT_OX":1528.8900599999997},"timestamp":96506},{"data":{"PT_IPA":6.289460000000001,"PT_N2O":-0.08107266666666667,"PT_CHAM":0.0045,"PT_N2":20.331920000000004,"PT_FUEL":1529.272896,"PT_OX":1528.8900599999997},"timestamp":97528},{"data":{"PT_IPA":6.289460000000001,"PT_N2O":-0.08107266666666667,"PT_CHAM":0.0045,"PT_N2":19.63088,"PT_FUEL":1529.2495596666668,"PT_OX":1528.8900599999997},"timestamp":98554},{"data":{"PT_IPA":6.289460000000001,"PT_N2O":-0.08107266666666667,"PT_CHAM":0.0045,"PT_N2":18.929840000000002,"PT_FUEL":1529.272896,"PT_OX":1528.8900599999997},"timestamp":99577},{"data":{"PT_IPA":6.289460000000001,"PT_N2O":-0.10438633333333333,"PT_CHAM":0.0045,"PT_N2":18.2288,"PT_FUEL":1529.272896,"PT_OX":1528.8900599999997},"timestamp":100695},{"data":{"PT_IPA":6.289460000000001,"PT_N2O":-0.10438633333333333,"PT_CHAM":0.0045,"PT_N2":17.52776,"PT_FUEL":1529.2495596666668,"PT_OX":1528.8900599999997},"timestamp":101624},{"data":{"PT_IPA":6.289460000000001,"PT_N2O":-0.08107266666666667,"PT_CHAM":0.0045,"PT_N2":17.0604,"PT_FUEL":1529.272896,"PT_OX":1528.8900599999997},"timestamp":102649},{"data":{"PT_IPA":6.289460000000001,"PT_N2O":-0.10438633333333333,"PT_CHAM":0.0045,"PT_N2":16.359360000000006,"PT_FUEL":1529.272896,"PT_OX":1528.8900599999997},"timestamp":103672},{"data":{"PT_IPA":6.289460000000001,"PT_N2O":-0.10438633333333333,"PT_CHAM":0.0045,"PT_N2":15.658320000000002,"PT_FUEL":1529.272896,"PT_OX":1528.8900599999997},"timestamp":104696},{"data":{"PT_IPA":6.289460000000001,"PT_N2O":-0.10438633333333333,"PT_CHAM":0.0045,"PT_N2":15.19096,"PT_FUEL":1529.2495596666668,"PT_OX":1528.8900599999997},"timestamp":105720},{"data":{"PT_IPA":6.289460000000001,"PT_N2O":-0.10438633333333333,"PT_CHAM":0.0045,"PT_N2":14.7236,"PT_FUEL":1529.2495596666668,"PT_OX":1528.8900599999997},"timestamp":106745},{"data":{"PT_IPA":6.289460000000001,"PT_N2O":-0.08107266666666667,"PT_CHAM":0.0045,"PT_N2":14.02256,"PT_FUEL":1529.272896,"PT_OX":1528.8900599999997},"timestamp":107770},{"data":{"PT_IPA":6.289460000000001,"PT_N2O":-0.10438633333333333,"PT_CHAM":0.0045,"PT_N2":13.555200000000001,"PT_FUEL":1529.2495596666668,"PT_OX":1528.8900599999997},"timestamp":108792},{"data":{"PT_IPA":6.289460000000001,"PT_N2O":-0.08107266666666667,"PT_CHAM":0.0045,"PT_N2":13.087840000000002,"PT_FUEL":1529.272896,"PT_OX":1528.8900599999997},"timestamp":109827},{"data":{"PT_IPA":6.289460000000001,"PT_N2O":-0.08107266666666667,"PT_CHAM":0.0045,"PT_N2":12.62048,"PT_FUEL":1529.272896,"PT_OX":1528.8900599999997},"timestamp":110840},{"data":{"PT_IPA":6.289460000000001,"PT_N2O":-0.08107266666666667,"PT_CHAM":0.0045,"PT_N2":12.15312,"PT_FUEL":1529.272896,"PT_OX":1528.8900599999997},"timestamp":111865},{"data":{"PT_IPA":6.289460000000001,"PT_N2O":-0.08107266666666667,"PT_CHAM":0.0045,"PT_N2":11.685760000000002,"PT_FUEL":1529.2495596666668,"PT_OX":1528.8900599999997},"timestamp":112888},{"data":{"PT_IPA":6.289460000000001,"PT_N2O":-0.08107266666666667,"PT_CHAM":0.0045,"PT_N2":11.2184,"PT_FUEL":1529.272896,"PT_OX":1528.8900599999997},"timestamp":113914},{"data":{"PT_IPA":6.289460000000001,"PT_N2O":-0.08107266666666667,"PT_CHAM":0.0045,"PT_N2":10.75104,"PT_FUEL":1529.272896,"PT_OX":1528.8900599999997},"timestamp":114937},{"data":{"PT_IPA":6.289460000000001,"PT_N2O":-0.08107266666666667,"PT_CHAM":0.0045,"PT_N2":10.28368,"PT_FUEL":1529.2495596666668,"PT_OX":1528.8900599999997},"timestamp":115961},{"data":{"PT_IPA":6.289460000000001,"PT_N2O":-0.10438633333333333,"PT_CHAM":0.0045,"PT_N2":9.81632,"PT_FUEL":1529.272896,"PT_OX":1528.8900599999997},"timestamp":116985},{"data":{"PT_IPA":6.289460000000001,"PT_N2O":-0.08107266666666667,"PT_CHAM":0.0045,"PT_N2":9.58264,"PT_FUEL":1529.2495596666668,"PT_OX":1528.8900599999997},"timestamp":118009},{"data":{"PT_IPA":6.289460000000001,"PT_N2O":-0.08107266666666667,"PT_CHAM":0.0045,"PT_N2":9.11528,"PT_FUEL":1529.272896,"PT_OX":1528.8900599999997},"timestamp":119033},{"data":{"PT_IPA":6.289460000000001,"PT_N2O":-0.08107266666666667,"PT_CHAM":0.0045,"PT_N2":8.414240000000001,"PT_FUEL":1529.272896,"PT_OX":1528.8900599999997},"timestamp":121081},{"data":{"PT_IPA":6.289460000000001,"PT_N2O":-0.08107266666666667,"PT_CHAM":0.0045,"PT_N2":8.18056,"PT_FUEL":1529.2495596666668,"PT_OX":1528.8900599999997},"timestamp":122105},{"data":{"PT_IPA":6.289460000000001,"PT_N2O":-0.08107266666666667,"PT_CHAM":0.0045,"PT_N2":7.946880000000002,"PT_FUEL":1529.2495596666668,"PT_OX":1528.8900599999997},"timestamp":123150},{"data":{"PT_IPA":6.289460000000001,"PT_N2O":-0.08107266666666667,"PT_CHAM":0.0045,"PT_N2":7.47952,"PT_FUEL":1529.272896,"PT_OX":1528.8900599999997},"timestamp":124153},{"data":{"PT_IPA":6.289460000000001,"PT_N2O":-0.08107266666666667,"PT_CHAM":0.0045,"PT_N2":7.24584,"PT_FUEL":1529.2495596666668,"PT_OX":1528.8900599999997},"timestamp":125179},{"data":{"PT_IPA":6.289460000000001,"PT_N2O":-0.10438633333333333,"PT_CHAM":0.0045,"PT_N2":7.01216,"PT_FUEL":1529.272896,"PT_OX":1528.8900599999997},"timestamp":126201},{"data":{"PT_IPA":6.289460000000001,"PT_N2O":-0.10438633333333333,"PT_CHAM":0.0045,"PT_N2":6.5448,"PT_FUEL":1529.272896,"PT_OX":1528.8900599999997},"timestamp":127225},{"data":{"PT_IPA":6.289460000000001,"PT_N2O":-0.10438633333333333,"PT_CHAM":0.0045,"PT_N2":6.311120000000001,"PT_FUEL":1529.272896,"PT_OX":1528.8900599999997},"timestamp":128271},{"data":{"PT_IPA":6.289460000000001,"PT_N2O":-0.08107266666666667,"PT_CHAM":0.0045,"PT_N2":6.07744,"PT_FUEL":1529.2495596666668,"PT_OX":1528.8900599999997},"timestamp":129273},{"data":{"PT_IPA":6.289460000000001,"PT_N2O":-0.10438633333333333,"PT_CHAM":0.0045,"PT_N2":5.84376,"PT_FUEL":1529.2495596666668,"PT_OX":1528.8900599999997},"timestamp":130299},{"data":{"PT_IPA":6.289460000000001,"PT_N2O":-0.10438633333333333,"PT_CHAM":0.0045,"PT_N2":5.610080000000001,"PT_FUEL":1529.272896,"PT_OX":1528.8900599999997},"timestamp":131321},{"data":{"PT_IPA":6.289460000000001,"PT_N2O":-0.10438633333333333,"PT_CHAM":0.0045,"PT_N2":5.3764,"PT_FUEL":1529.272896,"PT_OX":1528.8900599999997},"timestamp":132345},{"data":{"PT_IPA":6.289460000000001,"PT_N2O":-0.10438633333333333,"PT_CHAM":0.0045,"PT_N2":5.14272,"PT_FUEL":1529.272896,"PT_OX":1528.8900599999997},"timestamp":133403},{"data":{"PT_IPA":6.289460000000001,"PT_N2O":-0.08107266666666667,"PT_CHAM":0.0045,"PT_N2":4.90904,"PT_FUEL":1529.272896,"PT_OX":1528.8900599999997},"timestamp":134392},{"data":{"PT_IPA":6.289460000000001,"PT_N2O":-0.08107266666666667,"PT_CHAM":0.0045,"PT_N2":4.44168,"PT_FUEL":1529.2495596666668,"PT_OX":1528.8900599999997},"timestamp":136441},{"data":{"PT_IPA":6.289460000000001,"PT_N2O":-0.08107266666666667,"PT_CHAM":0.0045,"PT_N2":4.44168,"PT_FUEL":1529.272896,"PT_OX":1528.8900599999997},"timestamp":137473},{"data":{"PT_IPA":6.289460000000001,"PT_N2O":-0.10438633333333333,"PT_CHAM":0.0045,"PT_N2":4.207999999999999,"PT_FUEL":1529.272896,"PT_OX":1528.8900599999997},"timestamp":138489},{"data":{"PT_IPA":6.289460000000001,"PT_N2O":-0.10438633333333333,"PT_CHAM":0.0045,"PT_N2":3.9743200000000005,"PT_FUEL":1529.272896,"PT_OX":1528.8900599999997},"timestamp":139513},{"data":{"PT_IPA":6.289460000000001,"PT_N2O":-0.10438633333333333,"PT_CHAM":0.0045,"PT_N2":3.740640000000001,"PT_FUEL":1529.2495596666668,"PT_OX":1528.8900599999997},"timestamp":140537},{"data":{"PT_IPA":6.289460000000001,"PT_N2O":-0.08107266666666667,"PT_CHAM":0.0045,"PT_N2":3.740640000000001,"PT_FUEL":1529.272896,"PT_OX":1528.8900599999997},"timestamp":141561},{"data":{"PT_IPA":6.289460000000001,"PT_N2O":-0.08107266666666667,"PT_CHAM":0.0045,"PT_N2":3.5069600000000003,"PT_FUEL":1529.272896,"PT_OX":1528.8900599999997},"timestamp":142592},{"data":{"PT_IPA":6.289460000000001,"PT_N2O":-0.08107266666666667,"PT_CHAM":0.0045,"PT_N2":3.2732799999999997,"PT_FUEL":1529.2495596666668,"PT_OX":1528.8900599999997},"timestamp":143614},{"data":{"PT_IPA":6.289460000000001,"PT_N2O":-0.10438633333333333,"PT_CHAM":0.0045,"PT_N2":3.0396,"PT_FUEL":1529.272896,"PT_OX":1528.8900599999997},"timestamp":144636},{"data":{"PT_IPA":6.289460000000001,"PT_N2O":-0.08107266666666667,"PT_CHAM":0.0045,"PT_N2":3.0396,"PT_FUEL":1529.2495596666668,"PT_OX":1528.8900599999997},"timestamp":145659},{"data":{"PT_IPA":6.289460000000001,"PT_N2O":-0.10438633333333333,"PT_CHAM":0.0045,"PT_N2":2.8059200000000004,"PT_FUEL":1529.2495596666668,"PT_OX":1528.8900599999997},"timestamp":146732},{"data":{"PT_IPA":6.289460000000001,"PT_N2O":-0.10438633333333333,"PT_CHAM":0.0045,"PT_N2":2.8059200000000004,"PT_FUEL":1529.2495596666668,"PT_OX":1528.8900599999997},"timestamp":147708},{"data":{"PT_IPA":6.289460000000001,"PT_N2O":-0.08107266666666667,"PT_CHAM":0.0045,"PT_N2":2.33856,"PT_FUEL":1529.272896,"PT_OX":1528.8900599999997},"timestamp":149755},{"data":{"PT_IPA":6.289460000000001,"PT_N2O":-0.08107266666666667,"PT_CHAM":0.0045,"PT_N2":2.33856,"PT_FUEL":1529.2495596666668,"PT_OX":1528.8900599999997},"timestamp":150787},{"data":{"PT_IPA":6.289460000000001,"PT_N2O":-0.08107266666666667,"PT_CHAM":0.0045,"PT_N2":2.1048799999999996,"PT_FUEL":1529.272896,"PT_OX":1528.8900599999997},"timestamp":152834},{"data":{"PT_IPA":6.289460000000001,"PT_N2O":-0.10438633333333333,"PT_CHAM":0.0045,"PT_N2":1.8711999999999998,"PT_FUEL":1529.272896,"PT_OX":1528.8900599999997},"timestamp":153858},{"data":{"PT_IPA":6.289460000000001,"PT_N2O":-0.10438633333333333,"PT_CHAM":0.0045,"PT_N2":1.8711999999999998,"PT_FUEL":1529.2495596666668,"PT_OX":1528.8900599999997},"timestamp":155905},{"data":{"PT_IPA":6.289460000000001,"PT_N2O":-0.10438633333333333,"PT_CHAM":0.0045,"PT_N2":1.6375200000000005,"PT_FUEL":1529.272896,"PT_OX":1528.8900599999997},"timestamp":156928},{"data":{"PT_IPA":6.289460000000001,"PT_N2O":-0.10438633333333333,"PT_CHAM":0.0045,"PT_N2":1.40384,"PT_FUEL":1529.272896,"PT_OX":1528.8900599999997},"timestamp":158982},{"data":{"PT_IPA":6.289460000000001,"PT_N2O":-0.08107266666666667,"PT_CHAM":0.0045,"PT_N2":1.40384,"PT_FUEL":1529.2495596666668,"PT_OX":1528.8900599999997},"timestamp":160001},{"data":{"PT_IPA":6.289460000000001,"PT_N2O":-0.10438633333333333,"PT_CHAM":0.0045,"PT_N2":1.17016,"PT_FUEL":1529.272896,"PT_OX":1528.8900599999997},"timestamp":162044},{"data":{"PT_IPA":6.289460000000001,"PT_N2O":-0.10438633333333333,"PT_CHAM":0.0045,"PT_N2":1.17016,"PT_FUEL":1529.2495596666668,"PT_OX":1528.8900599999997},"timestamp":163158},{"data":{"PT_IPA":6.289460000000001,"PT_N2O":-0.08107266666666667,"PT_CHAM":0.0045,"PT_N2":1.17016,"PT_FUEL":1529.2495596666668,"PT_OX":1528.8900599999997},"timestamp":164096},{"data":{"PT_IPA":6.289460000000001,"PT_N2O":-0.08107266666666667,"PT_CHAM":0.0045,"PT_N2":0.93648,"PT_FUEL":1529.2495596666668,"PT_OX":1528.8900599999997},"timestamp":165118},{"data":{"PT_IPA":6.289460000000001,"PT_N2O":-0.10438633333333333,"PT_CHAM":0.0045,"PT_N2":0.93648,"PT_FUEL":1529.272896,"PT_OX":1528.8900599999997},"timestamp":166141},{"data":{"PT_IPA":6.289460000000001,"PT_N2O":-0.10438633333333333,"PT_CHAM":0.0045,"PT_N2":0.93648,"PT_FUEL":1529.272896,"PT_OX":1528.8900599999997},"timestamp":167165},{"data":{"PT_IPA":6.289460000000001,"PT_N2O":-0.08107266666666667,"PT_CHAM":0.0045,"PT_N2":0.7027999999999999,"PT_FUEL":1529.2495596666668,"PT_OX":1528.8900599999997},"timestamp":168238},{"data":{"PT_IPA":6.289460000000001,"PT_N2O":-0.08107266666666667,"PT_CHAM":0.0045,"PT_N2":0.7027999999999999,"PT_FUEL":1529.2495596666668,"PT_OX":1528.8900599999997},"timestamp":170253},{"data":{"PT_IPA":6.289460000000001,"PT_N2O":-0.10438633333333333,"PT_CHAM":0.0045,"PT_N2":0.7027999999999999,"PT_FUEL":1529.272896,"PT_OX":1528.8900599999997},"timestamp":171266},{"data":{"PT_IPA":6.289460000000001,"PT_N2O":-0.10438633333333333,"PT_CHAM":0.0045,"PT_N2":0.46912,"PT_FUEL":1529.2495596666668,"PT_OX":1528.8900599999997},"timestamp":172284},{"data":{"PT_IPA":6.289460000000001,"PT_N2O":-0.08107266666666667,"PT_CHAM":0.0045,"PT_N2":0.46912,"PT_FUEL":1529.272896,"PT_OX":1528.8900599999997},"timestamp":173392},{"data":{"PT_IPA":6.289460000000001,"PT_N2O":-0.10438633333333333,"PT_CHAM":0.0045,"PT_N2":0.46912,"PT_FUEL":1529.272896,"PT_OX":1528.8900599999997},"timestamp":174331},{"data":{"PT_IPA":6.289460000000001,"PT_N2O":-0.10438633333333333,"PT_CHAM":0.0045,"PT_N2":0.46912,"PT_FUEL":1529.272896,"PT_OX":1528.8900599999997},"timestamp":175355},{"data":{"PT_IPA":6.289460000000001,"PT_N2O":-0.08107266666666667,"PT_CHAM":0.0045,"PT_N2":0.46912,"PT_FUEL":1529.272896,"PT_OX":1528.8900599999997},"timestamp":176380},{"data":{"PT_IPA":6.289460000000001,"PT_N2O":-0.10438633333333333,"PT_CHAM":0.0045,"PT_N2":0.23543999999999998,"PT_FUEL":1529.2495596666668,"PT_OX":1528.8900599999997},"timestamp":177404},{"data":{"PT_IPA":6.289460000000001,"PT_N2O":-0.10438633333333333,"PT_CHAM":0.0045,"PT_N2":0.23543999999999998,"PT_FUEL":1529.272896,"PT_OX":1528.8900599999997},"timestamp":178427},{"data":{"PT_IPA":6.289460000000001,"PT_N2O":-0.08107266666666667,"PT_CHAM":0.0045,"PT_N2":0.23543999999999998,"PT_FUEL":1529.272896,"PT_OX":1528.8900599999997},"timestamp":179462},{"data":{"PT_IPA":6.289460000000001,"PT_N2O":-0.08107266666666667,"PT_CHAM":0.0045,"PT_N2":0.23543999999999998,"PT_FUEL":1529.272896,"PT_OX":1528.8900599999997},"timestamp":180474},{"data":{"PT_IPA":6.289460000000001,"PT_N2O":-0.08107266666666667,"PT_CHAM":0.0045,"PT_N2":0.23543999999999998,"PT_FUEL":1529.2495596666668,"PT_OX":1528.8900599999997},"timestamp":181502},{"data":{"PT_IPA":6.289460000000001,"PT_N2O":-0.08107266666666667,"PT_CHAM":0.0045,"PT_N2":0.23543999999999998,"PT_FUEL":1529.272896,"PT_OX":1528.8900599999997},"timestamp":182528},{"data":{"PT_IPA":6.289460000000001,"PT_N2O":-0.08107266666666667,"PT_CHAM":0.0045,"PT_N2":0.23543999999999998,"PT_FUEL":1529.2495596666668,"PT_OX":1528.8900599999997},"timestamp":183547},{"data":{"PT_IPA":6.289460000000001,"PT_N2O":-0.08107266666666667,"PT_CHAM":0.0045,"PT_N2":0.23543999999999998,"PT_FUEL":1529.2495596666668,"PT_OX":1528.8900599999997},"timestamp":184608},{"data":{"PT_IPA":6.289460000000001,"PT_N2O":-0.10438633333333333,"PT_CHAM":0.0045,"PT_N2":0.0017599999999999838,"PT_FUEL":1529.272896,"PT_OX":1528.8900599999997},"timestamp":185595},{"data":{"PT_IPA":6.289460000000001,"PT_N2O":-0.08107266666666667,"PT_CHAM":0.0045,"PT_N2":0.0017599999999999838,"PT_FUEL":1529.272896,"PT_OX":1528.8900599999997},"timestamp":186618},{"data":{"PT_IPA":6.289460000000001,"PT_N2O":-0.08107266666666667,"PT_CHAM":0.0045,"PT_N2":0.0017599999999999838,"PT_FUEL":1529.2495596666668,"PT_OX":1528.8900599999997},"timestamp":187643},{"data":{"PT_IPA":6.289460000000001,"PT_N2O":-0.10438633333333333,"PT_CHAM":0.0045,"PT_N2":0.0017599999999999838,"PT_FUEL":1529.2495596666668,"PT_OX":1528.8900599999997},"timestamp":188666},{"data":{"PT_IPA":6.289460000000001,"PT_N2O":-0.08107266666666667,"PT_CHAM":0.0045,"PT_N2":0.0017599999999999838,"PT_FUEL":1529.272896,"PT_OX":1528.8900599999997},"timestamp":189691},{"data":{"PT_IPA":6.289460000000001,"PT_N2O":-0.08107266666666667,"PT_CHAM":0.0045,"PT_N2":0.0017599999999999838,"PT_FUEL":1529.272896,"PT_OX":1528.8900599999997},"timestamp":190715},{"data":{"PT_IPA":6.289460000000001,"PT_N2O":-0.08107266666666667,"PT_CHAM":0.0045,"PT_N2":0.0017599999999999838,"PT_FUEL":1529.272896,"PT_OX":1528.8900599999997},"timestamp":191739},{"data":{"PT_IPA":6.289460000000001,"PT_N2O":-0.10438633333333333,"PT_CHAM":0.0045,"PT_N2":0.0017599999999999838,"PT_FUEL":1529.2495596666668,"PT_OX":1528.8900599999997},"timestamp":192763},{"data":{"PT_IPA":6.289460000000001,"PT_N2O":-0.10438633333333333,"PT_CHAM":0.0045,"PT_N2":0.0017599999999999838,"PT_FUEL":1529.272896,"PT_OX":1528.8900599999997},"timestamp":193786},{"data":{"PT_IPA":6.289460000000001,"PT_N2O":-0.10438633333333333,"PT_CHAM":0.0045,"PT_N2":0.0017599999999999838,"PT_FUEL":1529.272896,"PT_OX":1528.8900599999997},"timestamp":194810},{"data":{"PT_IPA":6.289460000000001,"PT_N2O":-0.10438633333333333,"PT_CHAM":0.0045,"PT_N2":0.0017599999999999838,"PT_FUEL":1529.272896,"PT_OX":1528.8900599999997},"timestamp":195837},{"data":{"PT_IPA":6.289460000000001,"PT_N2O":-0.10438633333333333,"PT_CHAM":0.0045,"PT_N2":0.0017599999999999838,"PT_FUEL":1529.2495596666668,"PT_OX":1528.8900599999997},"timestamp":196858},{"data":{"PT_IPA":6.289460000000001,"PT_N2O":-0.08107266666666667,"PT_CHAM":0.0045,"PT_N2":0.0017599999999999838,"PT_FUEL":1529.272896,"PT_OX":1528.8900599999997},"timestamp":197882}],"LOAD":[{"data":{"LOAD_CELL":170537.85657158095},"timestamp":247},{"data":{"LOAD_CELL":170537.85657158095},"timestamp":1270},{"data":{"LOAD_CELL":170537.85657158095},"timestamp":3319},{"data":{"LOAD_CELL":170537.85657158095},"timestamp":4342},{"data":{"LOAD_CELL":170537.85657158095},"timestamp":5366},{"data":{"LOAD_CELL":170537.85657158095},"timestamp":6390},{"data":{"LOAD_CELL":170537.85657158095},"timestamp":7415},{"data":{"LOAD_CELL":170537.85657158095},"timestamp":8438},{"data":{"LOAD_CELL":170537.85657158095},"timestamp":9462},{"data":{"LOAD_CELL":170537.85657158095},"timestamp":10487},{"data":{"LOAD_CELL":170537.85657158095},"timestamp":11510},{"data":{"LOAD_CELL":170537.85657158095},"timestamp":12535},{"data":{"LOAD_CELL":170537.85657158095},"timestamp":13558},{"data":{"LOAD_CELL":170537.85657158095},"timestamp":14589},{"data":{"LOAD_CELL":170537.85657158095},"timestamp":15607},{"data":{"LOAD_CELL":170537.85657158095},"timestamp":16630},{"data":{"LOAD_CELL":170537.85657158095},"timestamp":17656},{"data":{"LOAD_CELL":170537.85657158095},"timestamp":18679},{"data":{"LOAD_CELL":170537.85657158095},"timestamp":19703},{"data":{"LOAD_CELL":170537.85657158095},"timestamp":20727},{"data":{"LOAD_CELL":170537.85657158095},"timestamp":21751},{"data":{"LOAD_CELL":170537.85657158095},"timestamp":22775},{"data":{"LOAD_CELL":170537.85657158095},"timestamp":24848},{"data":{"LOAD_CELL":170537.85657158095},"timestamp":25848},{"data":{"LOAD_CELL":170537.85657158095},"timestamp":26871},{"data":{"LOAD_CELL":170537.85657158095},"timestamp":27896},{"data":{"LOAD_CELL":170537.85657158095},"timestamp":28919},{"data":{"LOAD_CELL":170537.85657158095},"timestamp":29944},{"data":{"LOAD_CELL":170537.85657158095},"timestamp":30967},{"data":{"LOAD_CELL":170537.85657158095},"timestamp":31991},{"data":{"LOAD_CELL":170537.85657158095},"timestamp":33016},{"data":{"LOAD_CELL":170537.85657158095},"timestamp":34040},{"data":{"LOAD_CELL":170537.85657158095},"timestamp":35064},{"data":{"LOAD_CELL":170537.85657158095},"timestamp":36093},{"data":{"LOAD_CELL":170537.85657158095},"timestamp":37111},{"data":{"LOAD_CELL":170537.85657158095},"timestamp":38136},{"data":{"LOAD_CELL":170537.85657158095},"timestamp":39159},{"data":{"LOAD_CELL":170537.85657158095},"timestamp":40197},{"data":{"LOAD_CELL":170537.85657158095},"timestamp":41224},{"data":{"LOAD_CELL":170537.85657158095},"timestamp":42230},{"data":{"LOAD_CELL":170537.85657158095},"timestamp":43254},{"data":{"LOAD_CELL":170537.85657158095},"timestamp":44279},{"data":{"LOAD_CELL":170537.85657158095},"timestamp":46327},{"data":{"LOAD_CELL":170537.85657158095},"timestamp":47351},{"data":{"LOAD_CELL":170537.85657158095},"timestamp":48375},{"data":{"LOAD_CELL":170537.85657158095},"timestamp":50423},{"data":{"LOAD_CELL":170537.85657158095},"timestamp":51476},{"data":{"LOAD_CELL":170537.85657158095},"timestamp":53522},{"data":{"LOAD_CELL":170537.85657158095},"timestamp":54519},{"data":{"LOAD_CELL":170537.85657158095},"timestamp":56568},{"data":{"LOAD_CELL":170537.85657158095},"timestamp":57620},{"data":{"LOAD_CELL":170537.85657158095},"timestamp":59642},{"data":{"LOAD_CELL":170537.85657158095},"timestamp":60665},{"data":{"LOAD_CELL":170537.85657158095},"timestamp":62712},{"data":{"LOAD_CELL":170537.85657158095},"timestamp":63766},{"data":{"LOAD_CELL":170537.85657158095},"timestamp":65785},{"data":{"LOAD_CELL":170537.85657158095},"timestamp":67833},{"data":{"LOAD_CELL":170537.85657158095},"timestamp":68857},{"data":{"LOAD_CELL":170537.85657158095},"timestamp":69909},{"data":{"LOAD_CELL":170537.85657158095},"timestamp":70911},{"data":{"LOAD_CELL":170537.85657158095},"timestamp":71929},{"data":{"LOAD_CELL":170537.85657158095},"timestamp":72952},{"data":{"LOAD_CELL":170537.85657158095},"timestamp":73978},{"data":{"LOAD_CELL":170537.85657158095},"timestamp":75032},{"data":{"LOAD_CELL":170537.85657158095},"timestamp":76025},{"data":{"LOAD_CELL":170537.85657158095},"timestamp":77050},{"data":{"LOAD_CELL":170537.85657158095},"timestamp":78073},{"data":{"LOAD_CELL":170537.85657158095},"timestamp":79097},{"data":{"LOAD_CELL":170537.85657158095},"timestamp":80167},{"data":{"LOAD_CELL":170537.85657158095},"timestamp":81144},{"data":{"LOAD_CELL":170537.85657158095},"timestamp":82168},{"data":{"LOAD_CELL":170537.85657158095},"timestamp":83193},{"data":{"LOAD_CELL":170537.85657158095},"timestamp":84218},{"data":{"LOAD_CELL":170537.85657158095},"timestamp":85273},{"data":{"LOAD_CELL":170537.85657158095},"timestamp":86265},{"data":{"LOAD_CELL":170537.85657158095},"timestamp":87305},{"data":{"LOAD_CELL":170537.85657158095},"timestamp":88312},{"data":{"LOAD_CELL":170537.85657158095},"timestamp":89337},{"data":{"LOAD_CELL":170537.85657158095},"timestamp":90392},{"data":{"LOAD_CELL":170537.85657158095},"timestamp":91386},{"data":{"LOAD_CELL":170537.85657158095},"timestamp":92409},{"data":{"LOAD_CELL":170537.85657158095},"timestamp":93434},{"data":{"LOAD_CELL":170537.85657158095},"timestamp":94459},{"data":{"LOAD_CELL":170537.85657158095},"timestamp":95538},{"data":{"LOAD_CELL":170537.85657158095},"timestamp":96507},{"data":{"LOAD_CELL":170537.85657158095},"timestamp":97529},{"data":{"LOAD_CELL":170537.85657158095},"timestamp":98555},{"data":{"LOAD_CELL":170537.85657158095},"timestamp":99578},{"data":{"LOAD_CELL":170537.85657158095},"timestamp":100696},{"data":{"LOAD_CELL":170537.85657158095},"timestamp":101625},{"data":{"LOAD_CELL":170537.85657158095},"timestamp":102650},{"data":{"LOAD_CELL":170537.85657158095},"timestamp":103673},{"data":{"LOAD_CELL":170537.85657158095},"timestamp":104697},{"data":{"LOAD_CELL":170537.85657158095},"timestamp":105721},{"data":{"LOAD_CELL":170537.85657158095},"timestamp":106746},{"data":{"LOAD_CELL":170537.85657158095},"timestamp":107771},{"data":{"LOAD_CELL":170537.85657158095},"timestamp":108794},{"data":{"LOAD_CELL":170537.85657158095},"timestamp":109828},{"data":{"LOAD_CELL":170537.85657158095},"timestamp":110841},{"data":{"LOAD_CELL":170537.85657158095},"timestamp":111866},{"data":{"LOAD_CELL":170537.85657158095},"timestamp":112890},{"data":{"LOAD_CELL":170537.85657158095},"timestamp":113915},{"data":{"LOAD_CELL":170537.85657158095},"timestamp":114938},{"data":{"LOAD_CELL":170537.85657158095},"timestamp":115962},{"data":{"LOAD_CELL":170537.85657158095},"timestamp":116986},{"data":{"LOAD_CELL":170537.85657158095},"timestamp":118010},{"data":{"LOAD_CELL":170537.85657158095},"timestamp":119034},{"data":{"LOAD_CELL":170537.85657158095},"timestamp":121082},{"data":{"LOAD_CELL":170537.85657158095},"timestamp":122106},{"data":{"LOAD_CELL":170537.85657158095},"timestamp":123151},{"data":{"LOAD_CELL":170537.85657158095},"timestamp":124154},{"data":{"LOAD_CELL":170537.85657158095},"timestamp":125180},{"data":{"LOAD_CELL":170537.85657158095},"timestamp":126202},{"data":{"LOAD_CELL":170537.85657158095},"timestamp":127226},{"data":{"LOAD_CELL":170537.85657158095},"timestamp":128272},{"data":{"LOAD_CELL":170537.85657158095},"timestamp":129274},{"data":{"LOAD_CELL":170537.85657158095},"timestamp":130300},{"data":{"LOAD_CELL":170537.85657158095},"timestamp":131322},{"data":{"LOAD_CELL":170537.85657158095},"timestamp":132346},{"data":{"LOAD_CELL":170537.85657158095},"timestamp":133404},{"data":{"LOAD_CELL":170537.85657158095},"timestamp":134393},{"data":{"LOAD_CELL":170537.85657158095},"timestamp":136442},{"data":{"LOAD_CELL":170537.85657158095},"timestamp":137474},{"data":{"LOAD_CELL":170537.85657158095},"timestamp":138490},{"data":{"LOAD_CELL":170537.85657158095},"timestamp":139514},{"data":{"LOAD_CELL":170537.85657158095},"timestamp":140538},{"data":{"LOAD_CELL":170537.85657158095},"timestamp":141564},{"data":{"LOAD_CELL":170537.85657158095},"timestamp":142594},{"data":{"LOAD_CELL":170537.85657158095},"timestamp":143615},{"data":{"LOAD_CELL":170537.85657158095},"timestamp":144637},{"data":{"LOAD_CELL":170537.85657158095},"timestamp":145660},{"data":{"LOAD_CELL":170537.85657158095},"timestamp":146733},{"data":{"LOAD_CELL":170537.85657158095},"timestamp":147709},{"data":{"LOAD_CELL":170537.85657158095},"timestamp":149758},{"data":{"LOAD_CELL":170537.85657158095},"timestamp":150788},{"data":{"LOAD_CELL":170537.85657158095},"timestamp":152836},{"data":{"LOAD_CELL":170537.85657158095},"timestamp":153859},{"data":{"LOAD_CELL":170537.85657158095},"timestamp":155906},{"data":{"LOAD_CELL":170537.85657158095},"timestamp":156929},{"data":{"LOAD_CELL":170537.85657158095},"timestamp":158983},{"data":{"LOAD_CELL":170537.85657158095},"timestamp":160002},{"data":{"LOAD_CELL":170537.85657158095},"timestamp":162045},{"data":{"LOAD_CELL":170537.85657158095},"timestamp":163159},{"data":{"LOAD_CELL":170537.85657158095},"timestamp":164097},{"data":{"LOAD_CELL":170537.85657158095},"timestamp":165119},{"data":{"LOAD_CELL":170537.85657158095},"timestamp":166142},{"data":{"LOAD_CELL":170537.85657158095},"timestamp":167166},{"data":{"LOAD_CELL":170537.85657158095},"timestamp":168239},{"data":{"LOAD_CELL":170537.85657158095},"timestamp":170254},{"data":{"LOAD_CELL":170537.85657158095},"timestamp":171267},{"data":{"LOAD_CELL":170537.85657158095},"timestamp":172285},{"data":{"LOAD_CELL":170537.85657158095},"timestamp":173393},{"data":{"LOAD_CELL":170537.85657158095},"timestamp":174333},{"data":{"LOAD_CELL":170537.85657158095},"timestamp":175355},{"data":{"LOAD_CELL":170537.85657158095},"timestamp":176381},{"data":{"LOAD_CELL":170537.85657158095},"timestamp":177404},{"data":{"LOAD_CELL":170537.85657158095},"timestamp":178428},{"data":{"LOAD_CELL":170537.85657158095},"timestamp":179463},{"data":{"LOAD_CELL":170537.85657158095},"timestamp":180475},{"data":{"LOAD_CELL":170537.85657158095},"timestamp":181504},{"data":{"LOAD_CELL":170537.85657158095},"timestamp":182529},{"data":{"LOAD_CELL":170537.85657158095},"timestamp":183548},{"data":{"LOAD_CELL":170537.85657158095},"timestamp":184609},{"data":{"LOAD_CELL":170537.85657158095},"timestamp":185596},{"data":{"LOAD_CELL":170537.85657158095},"timestamp":186619},{"data":{"LOAD_CELL":170537.85657158095},"timestamp":187644},{"data":{"LOAD_CELL":170537.85657158095},"timestamp":188667},{"data":{"LOAD_CELL":170537.85657158095},"timestamp":189692},{"data":{"LOAD_CELL":170537.85657158095},"timestamp":190716},{"data":{"LOAD_CELL":170537.85657158095},"timestamp":191741},{"data":{"LOAD_CELL":170537.85657158095},"timestamp":192764},{"data":{"LOAD_CELL":170537.85657158095},"timestamp":193787},{"data":{"LOAD_CELL":170537.85657158095},"timestamp":194811},{"data":{"LOAD_CELL":170537.85657158095},"timestamp":195837},{"data":{"LOAD_CELL":170537.85657158095},"timestamp":196859},{"data":{"LOAD_CELL":170537.85657158095},"timestamp":197883}]}